Workbook

Sheet Summary
A4: Proposal for Agent/Banca Portal & Back-office Solution: Bill of Materials
A5: iorta TechNXT – proposal to Insurans Islam Family Takaful Sendirian Berhad – October 2026
A7: Client | B7: Insurans Islam Family Takaful Sendirian Berhad
A8: Bidder | B8: iorta TechNXT
A9: Solution | B9: SalesVerse 2.0, configured as the IIFT Agent/Banca Portal & Back-office
A10: Currency | B10: Brunei Dollar (B$), indicative amounts
A12: Option A – on-premise (B$)
A13: Category | B13: Treatment | C13: One-time low | D13: One-time high | E13: Per year low | F13: Per year high | G13: Five years low | H13: Five years high
A14: On-premise infrastructure (servers, storage, DR) | B14: IIFT procures | C14: ='On-premise infrastructure'!$L$19 | D14: ='On-premise infrastructure'!$M$19 | E14: 0 | F14: 0 | G14: =C14+5*E14 | H14: =D14+5*F14
A15: Operating system (Ubuntu Server LTS) | B15: IIFT procures | C15: 0 | D15: 0 | E15: 0 | F15: 0 | G15: =C15+5*E15 | H15: =D15+5*F15
A16: Runtime software licences (open source) | B16: Included in iorta fee | C16: 0 | D16: 0 | E16: 0 | F16: 0 | G16: =C16+5*E16 | H16: =D16+5*F16
A17: Third-party services – required (SMS, AML data, certificates, e-mail) | B17: IIFT procures / at cost | C17: 0 | D17: 0 | E17: ='Third-party services'!$E$22 | F17: ='Third-party services'!$F$22 | G17: =C17+5*E17 | H17: =D17+5*F17
A18: Total Option A, required items | C18: =C14+C15+C16+C17 | D18: =D14+D15+D16+D17 | E18: =E14+E15+E16+E17 | F18: =F14+F15+F16+F17 | G18: =G14+G15+G16+G17 | H18: =H14+H15+H16+H17
A19: Optional items (PostgreSQL support, RHEL, escrow) | B19: Only if IIFT elects | C19: 0 | D19: 0 | E19: ='Third-party services'!$E$23 | F19: ='Third-party services'!$F$23 | G19: =C19+5*E19 | H19: =D19+5*F19
A21: Option B – iorta-hosted cloud (B$)
A22: Category | B22: Treatment | C22: One-time low | D22: One-time high | E22: Per year low | F22: Per year high | G22: Five years low | H22: Five years high
A23: Cloud services at cost (estimate) | B23: Disbursement at cost or paid by IIFT directly | C23: ='Cloud services (Option B)'!$F$17 | D23: ='Cloud services (Option B)'!$F$17 | E23: ='Cloud services (Option B)'!$F$16 | F23: ='Cloud services (Option B)'!$F$16 | G23: =C23+5*E23 | H23: =D23+5*F23
A24: Runtime software licences (open source) | B24: Included in iorta fee | C24: 0 | D24: 0 | E24: 0 | F24: 0 | G24: =C24+5*E24 | H24: =D24+5*F24
A25: Third-party services – required (SMS, AML data, e-mail) | B25: IIFT procures | C25: 0 | D25: 0 | E25: ='Third-party services'!$H$22 | F25: ='Third-party services'!$I$22 | G25: =C25+5*E25 | H25: =D25+5*F25
A26: Total Option B, required items | C26: =C23+C24+C25 | D26: =D23+D24+D25 | E26: =E23+E24+E25 | F26: =F23+F24+F25 | G26: =G23+G24+G25 | H26: =H23+H24+H25
A27: Optional items (escrow) | B27: Only if IIFT elects | C27: 0 | D27: 0 | E27: ='Third-party services'!$H$23 | F27: ='Third-party services'!$I$23 | G27: =C27+5*E27 | H27: =D27+5*F27
A29: Notes
A30: • Infrastructure and third-party items are paid by IIFT directly or passed through by iorta at cost, without mark-up. They are not included in iorta's fees in the pricing workbook.
A31: • Independent VAPT and re-test before go-live, the monitoring stack and the CI/CD tooling are included in iorta's fees.
A32: • Under Option B, the one-off cloud set-up fee (B$ 15,000) and iorta's managed services are iorta fees in the pricing workbook, not in this BOM. Cloud charges are recharged at cost as disbursements with provider invoices attached, or paid by IIFT directly if it holds the account.
A33: • Sizing basis: 26 named users, about 628 policies a year; designed for 100 concurrent and 500 named users. Ranges are indicative for budgeting.

Sheet On-premise infrastructure
A1: On-premise infrastructure for Option A – procured by IIFT to iorta's sizing
A2: iorta TechNXT – proposal to Insurans Islam Family Takaful Sendirian Berhad – October 2026
A4: Sizing as in the Solution Architecture (Infrastructure Sizing). Costs are indicative one-time amounts if capacity is provisioned new, for IIFT's budgeting; they are lower where existing IITH virtualisation, storage, backup and security capacity is reused. They are not part of iorta's fees.
A6: Environment | B6: Server / item | C6: Qty | D6: vCPU | E6: RAM (GB) | F6: Storage | G6: Software | H6: OS licence | I6: Total vCPU | J6: Unit cost low (B$) | K6: Unit cost high (B$) | L6: Total low (B$) | M6: Total high (B$) | N6: Notes
A7: Production | B7: WAF / load balancer | C7: 2 | D7: 2 | E7: 4 | F7: – | G7: IITH appliance or HAProxy/nginx pair | H7: No | I7: =C7*D7 | J7: 0 | K7: 1000 | L7: =C7*J7 | M7: =C7*K7 | N7: Quantity: 2 (or existing). B$0 where the IITH WAF / F5 is reused (recommended)
A8: Production | B8: Application VM | C8: 2 | D8: 4 | E8: 8 | F8: 100 GB | G8: Linux, Docker Engine; web, api, clamav containers | H8: Yes | I8: =C8*D8 | J8: 1500 | K8: 3000 | L8: =C8*J8 | M8: =C8*K8
A9: Production | B9: Database VM | C9: 2 | D9: 4 | E9: 16 | F9: 200 GB SSD | G9: PostgreSQL 16 primary and hot standby, pgBackRest | H9: Yes | I9: =C9*D9 | J9: 2500 | K9: 4500 | L9: =C9*J9 | M9: =C9*K9
A10: Production | B10: Document store | C10: 1 | F10: 500 GB | G10: NFS export, encrypted volume | H10: No | J10: 1000 | K10: 2000 | L10: =C10*J10 | M10: =C10*K10 | N10: Quantity: 1 share.
A11: Production | B11: Backup repository | C11: 1 | F11: 1 TB | G11: pgBackRest repository, document backups | H11: No | J11: 1500 | K11: 3000 | L11: =C11*J11 | M11: =C11*K11 | N11: Lower where IITH backup capacity is reused
A12: Production | B12: Monitoring | C12: 1 | D12: 2 | E12: 4 | F12: 100 GB | G12: Prometheus, Grafana, log collector | H12: Yes | I12: =C12*D12 | J12: 0 | K12: 1500 | L12: =C12*J12 | M12: =C12*K12 | N12: Quantity: 1 (or existing). B$0 where IITH monitoring is reused
A13: Non-production | B13: SIT | C13: 1 | D13: 4 | E13: 16 | F13: 200 GB | G13: Compose: web, api, clamav, PostgreSQL | H13: Yes | I13: =C13*D13 | J13: 2000 | K13: 3500 | L13: =C13*J13 | M13: =C13*K13
A14: Non-production | B14: UAT | C14: 1 | D14: 4 | E14: 16 | F14: 200 GB | G14: Compose: web, api, clamav, PostgreSQL | H14: Yes | I14: =C14*D14 | J14: 2000 | K14: 3500 | L14: =C14*J14 | M14: =C14*K14
A15: Non-production | B15: DEV | C15: 0 | F15: – | G15: Hosted by iorta during the project and support | H15: No | J15: 0 | K15: 0 | L15: =C15*J15 | M15: =C15*K15 | N15: Quantity: Not required. No IIFT infrastructure needed
A16: DR site | B16: Application VM | C16: 1 | D16: 4 | E16: 8 | F16: 100 GB | G16: Cold standby, same images | H16: Yes | I16: =C16*D16 | J16: 1500 | K16: 3000 | L16: =C16*J16 | M16: =C16*K16
A17: DR site | B17: Database VM | C17: 1 | D17: 4 | E17: 16 | F17: 200 GB SSD | G17: Asynchronous replica | H17: Yes | I17: =C17*D17 | J17: 2500 | K17: 4500 | L17: =C17*J17 | M17: =C17*K17
A18: DR site | B18: Document and backup copies | C18: 1 | F18: 500 GB + 1 TB | G18: rsync target, backup copy | H18: No | J18: 2000 | K18: 4000 | L18: =C18*J18 | M18: =C18*K18
A19: Total | C19: =SUM(C7:C18) | E19: =SUM(E7:E18) | I19: =SUM(I7:I18) | L19: =SUM(L7:L18) | M19: =SUM(M7:M18) | N19: Indicative one-time cost, IIFT's own procurement
A21: Operating system
A22: VMs needing an OS licence | C22: =C8+C9+C12+C13+C14+C16+C17 | N22: Application, database, monitoring, SIT, UAT and DR VMs
A23: Ubuntu Server 24.04 LTS | B23: Recommended | G23: No licence fee | J23: 0 | K23: 0 | L23: =C22*J23 | M23: =C22*K23 | N23: Optional Ubuntu Pro support not required
A24: RHEL 9 subscriptions | B24: Optional, per VM per year | G24: Only if IIFT standardises on RHEL | J24: 500 | K24: 1200 | L24: =C22*J24 | M24: =C22*K24 | N24: Annual; IIFT procures
A26: Reused IITH services (no new procurement expected)
A27: • Virtualisation platform, network, firewall, DNS and the DMZ.
A28: • WAF / load balancer (F5 or equivalent): reuse recommended; otherwise an HAProxy/nginx pair on two small VMs.
A29: • Enterprise backup platform and off-site copies; pgBackRest (open source) handles PostgreSQL backups.
A30: • SIEM and infrastructure monitoring; iorta configures log and metric forwarding.
A31: • DEV environment: hosted by iorta, so IIFT provides none.

Sheet Cloud services (Option B)
A1: Cloud services for Option B – recharged at cost (AWS Asia Pacific (Malaysia) or Azure Malaysia West)
A2: iorta TechNXT – proposal to Insurans Islam Family Takaful Sendirian Berhad – October 2026
A4: Estimate for budgeting. iorta recharges the provider's charges monthly in arrears at cost as a disbursement, with the provider invoice attached and no mark-up, outside the fees to which WHT applies. Alternatively IIFT holds the cloud account in its own name and pays the provider directly. The one-off cloud set-up (B$ 15,000) and iorta's managed services are fees in the pricing workbook.
A6: No | B6: Service | C6: Purpose | D6: Reference sizing | E6: B$ per month | F6: B$ per year | G6: Billing basis
A7: 1 | B7: Container compute, 2 tasks across 2 availability zones | C7: Portal, back-office and API | D7: 2 tasks × (1 vCPU, 2 GB) incl. ClamAV sidecar; scales to 4 tasks | E7: 260 | F7: =E7*12 | G7: At cost as a disbursement (provider invoice attached, no mark-up), or paid by IIFT directly
A8: 2 | B8: Managed PostgreSQL, Multi-AZ, 100 GB, automated backups | C8: Database and point-in-time recovery | D8: db.t4g.large (2 vCPU, 8 GB), Multi-AZ, 100 GB gp3, 35-day backups and PITR | E8: 420 | F8: =E8*12 | G8: At cost as a disbursement (provider invoice attached, no mark-up), or paid by IIFT directly
A9: 3 | B9: Application load balancer and web application firewall | C9: TLS termination, OWASP rules | D9: 1 load balancer; WAF with managed OWASP rule sets; managed TLS certificate | E9: 130 | F9: =E9*12 | G9: At cost as a disbursement (provider invoice attached, no mark-up), or paid by IIFT directly
A10: 4 | B10: NAT gateway and data transfer | C10: Outbound integration and updates | D10: NAT gateway, site-to-site VPN to the IITH data centre, outbound data | E10: 90 | F10: =E10*12 | G10: At cost as a disbursement (provider invoice attached, no mark-up), or paid by IIFT directly
A11: 5 | B11: Object storage (encrypted) and cross-region backup copies | C11: Documents, backups, DR copies | D11: Shared file storage up to 100 GB; about 200 GB object storage; cross-region copy | E11: 70 | F11: =E11*12 | G11: At cost as a disbursement (provider invoice attached, no mark-up), or paid by IIFT directly
A12: 6 | B12: Logging, metrics, alarms and threat detection | C12: Monitoring and security | D12: Log retention 90 days, metrics, alarms, threat detection | E12: 70 | F12: =E12*12 | G12: At cost as a disbursement (provider invoice attached, no mark-up), or paid by IIFT directly
A13: 7 | B13: Secrets and key management | C13: Credentials and encryption keys | D13: Secrets store and encryption keys held in IIFT's account | E13: 20 | F13: =E13*12 | G13: At cost as a disbursement (provider invoice attached, no mark-up), or paid by IIFT directly
A14: 8 | B14: UAT environment, scaled down, stopped out of hours | C14: Non-production testing | D14: 1 task and a single-AZ db.t4g.medium; stopped outside test periods | E14: 120 | F14: =E14*12 | G14: At cost as a disbursement (provider invoice attached, no mark-up), or paid by IIFT directly
A15: 9 | B15: DR environment, pilot light in a second region | C15: Database replica and standby images | D15: Cross-region database replica or snapshots and standby images | E15: 150 | F15: =E15*12 | G15: At cost as a disbursement (provider invoice attached, no mark-up), or paid by IIFT directly
B16: Total, production run | E16: =SUM(E7:E15) | F16: =SUM(F7:F15)
B17: Project environments (DEV, SIT, UAT) before go-live | C17: Implementation period | D17: Scaled down, 5 months | E17: 300 | F17: =E17*5 | G17: One-off total for the project period
B18: Estimate, project plus five years | F18: =F17+5*F16
A20: • Region: AWS Asia Pacific (Malaysia) ap-southeast-5 or Azure Malaysia West; DR copies in a second region subject to IIFT approval. A Brunei-hosted alternative can be priced on request.
A21: • Providers bill in USD; charges are converted to B$ at the bank selling rate on the provider's invoice date.
A22: • Budget alerts at 80% and 100% of the estimate; monthly cost report; quarterly right-sizing review.

Sheet Software & licences
A1: Software components and licences
A2: iorta TechNXT – proposal to Insurans Islam Family Takaful Sendirian Berhad – October 2026
A4: Every runtime component of the solution. All are open source with no licence fee; the operating system is the only item with a paid choice (RHEL).
A6: 1. Runtime components
A7: Component | B7: Version | C7: Role | D7: Licence | E7: Licence fee (B$) | F7: Treatment
A8: Node.js | B8: 22 LTS | C8: API runtime (inside the container image) | D8: MIT | E8: 0 | F8: Included in iorta fee
A9: NestJS | B9: 12 | C9: API framework | D9: MIT | E9: 0 | F9: Included in iorta fee
A10: Prisma ORM and PostgreSQL driver adapter | B10: 7 | C10: Data access and migrations | D10: Apache-2.0 | E10: 0 | F10: Included in iorta fee
A11: React and React DOM | B11: 19 | C11: Portal and back-office user interface | D11: MIT | E11: 0 | F11: Included in iorta fee
A12: Ant Design and Ant Design Icons | B12: 6 | C12: UI component library | D12: MIT | E12: 0 | F12: Included in iorta fee
A13: TanStack Query, React Router, Recharts, Day.js | B13: 5 / 7 / 3 / 1 | C13: UI data, routing, charts, dates | D13: MIT | E13: 0 | F13: Included in iorta fee
A14: pdfkit, exceljs | B14: 0.20 / 4.4 | C14: PDF documents and Excel reports | D14: MIT | E14: 0 | F14: Included in iorta fee
A15: Argon2 (@node-rs/argon2), helmet, express-session | B15: 2 / 8 / 1 | C15: Password hashing, security headers, sessions | D15: MIT | E15: 0 | F15: Included in iorta fee
A16: pino, prom-client | B16: 10 / 15 | C16: Structured logs and metrics | D16: MIT / Apache-2.0 | E16: 0 | F16: Included in iorta fee
A17: ldapts, nodemailer | B17: 9 / 10 | C17: Active Directory and e-mail integration | D17: MIT / MIT-0 | E17: 0 | F17: Included in iorta fee
A18: PostgreSQL | B18: 16 | C18: Database | D18: PostgreSQL Licence | E18: 0 | F18: Included in iorta fee
A19: pgBackRest | B19: 2 | C19: Database backup and point-in-time recovery | D19: MIT | E19: 0 | F19: Included in iorta fee
... A24: Prometheus, Grafana, Loki | B24: current | C24: Monitoring, dashboards, log aggregation | D24: Apache-2.0 / AGPL-3.0 | E24: 0 | F24: Included in iorta fee
A25: Total licence fees | E25: =SUM(E8:E24)
A27: 2. Application packages by licence (494 runtime npm packages, from the CI licence scan)
A28: Licence | B28: Packages | C28: Type
A29: MIT | B29: 400 | C29: Permissive
A30: ISC | B30: 40 | C30: Permissive
A31: Apache-2.0 | B31: 30 | C31: Permissive
A32: BSD-3-Clause | B32: 7 | C32: Permissive
A33: Unlicense | B33: 3 | C33: Permissive
A34: UNKNOWN | B34: 2 | C34: Not declared in package metadata; reviewed in the SBOM licence check before go-live
A35: MIT/X11 | B35: 2 | C35: Permissive
A36: BSD-2-Clause | B36: 2 | C36: Permissive
A37: MIT and ISC | B37: 1 | C37: Permissive
A38: Python-2.0 | B38: 1 | C38: Permissive
A39: EPL-2.0 | B39: 1 | C39: Weak copyleft; used unmodified as a library
A40: (MIT OR GPL-3.0-or-later) | B40: 1 | C40: Dual licence; used under MIT
... A44: MIT AND ISC | B44: 1 | C44: Permissive
A45: Total | B45: =SUM(B29:B44)
A47: 3. Notes
A48: • Direct runtime dependencies: 28 in the API (apps/api/package.json) and 8 in the web application (apps/web/package.json).
A49: • Packages that are not plainly permissive: UNKNOWN: buffers 0.1.1, png-js 2.0.0; EPL-2.0: elkjs 0.11.1; (MIT OR GPL-3.0-or-later): jszip 3.10.2.
A50: • ClamAV (GPL-2.0) and Grafana / Loki (AGPL-3.0) run as separate, unmodified programs; IITH monitoring tools can replace Grafana and Loki.
A51: • The CI pipeline produces a CycloneDX SBOM (npm sbom, production dependencies) on every build; it is delivered with each release.

Sheet Third-party services
A1: Third-party services, paid and optional items – indicative B$ per year
A2: iorta TechNXT – proposal to Insurans Islam Family Takaful Sendirian Berhad – October 2026
A4: Treatment: Included in iorta fee / Pass-through at cost / IIFT procures / Not required. Amounts are indicative and confirmed by each provider; they are not part of iorta's fees unless marked included.
A6: Item | B6: Basis | C6: Required | D6: Option A treatment | E6: A: low (B$) | F6: A: high (B$) | G6: Option B treatment | H6: B: low (B$) | I6: B: high (B$) | J6: Notes
A7: SSL/TLS certificates | B7: Annual, per certificate | C7: Yes | D7: IIFT procures | E7: 300 | F7: 1000 | G7: Pass-through at cost | H7: 0 | I7: 0 | J7: Two public certificates (portal, e-signature link) at about B$150–500 each; internal certificates from the IITH CA. Under Option B the load-balancer certificate is issued by the cloud provider at no charge.
A8: SMS gateway | B8: Per message | C8: Yes | D8: IIFT procures | E8: 300 | F8: 600 | G8: IIFT procures | H8: 300 | I8: 600 | J8: IIFT's SMS provider account; about B$0.05–0.10 per message, roughly 6,000 OTP and alert messages a year.
A9: AML screening data / service | B9: Annual or per search | C9: Yes | D9: IIFT procures | E9: 0 | F9: 3000 | G9: IIFT procures | H9: 0 | I9: 3000 | J9: B$0 if IIFT's existing screening service or lists are reused; otherwise from about B$3,000 a year.
A10: E-mail relay | B10: Usage | C10: Yes | D10: IIFT procures | E10: 0 | F10: 120 | G10: IIFT procures | H10: 0 | I10: 120 | J10: B$0 through the IITH relay (over the VPN under Option B); a cloud e-mail service costs under B$10 a month.
A11: Independent VAPT and re-test | B11: One-off | C11: Yes | D11: Included in iorta fee | E11: 0 | F11: 0 | G11: Included in iorta fee | H11: 0 | I11: 0 | J11: Pre-go-live test and re-test included in item 7. Later annual tests can be quoted on request.
A12: Backup software | B12: – | C12: Yes | D12: IIFT procures | E12: 0 | F12: 0 | G12: Pass-through at cost | H12: 0 | I12: 0 | J12: Option A: IITH backup platform reused; pgBackRest (open source) for PostgreSQL. Option B: cloud backup services within the cloud actuals.
A13: SIEM / security monitoring | B13: – | C13: Yes | D13: IIFT procures | E13: 0 | F13: 0 | G13: Pass-through at cost | H13: 0 | I13: 0 | J13: Option A: IITH SIEM reused; iorta configures log forwarding. Option B: cloud threat detection within the cloud actuals; forwarding to the IITH SIEM on request.
A14: Virtualisation, network, firewall, DNS | B14: – | C14: Yes | D14: IIFT procures | E14: 0 | F14: 0 | G14: IIFT procures | H14: 0 | I14: 0 | J14: Existing IITH platforms. Under Option B only the IITH VPN endpoint and DNS entries are needed.
A15: Source code repository and CI/CD | B15: – | C15: Yes | D15: Included in iorta fee | E15: 0 | F15: 0 | G15: Included in iorta fee | H15: 0 | I15: 0 | J15: iorta's repository and pipeline during the contract, mirrored to IITH GitLab if required.
A16: Monitoring stack (Prometheus, Grafana, Loki) | B16: – | C16: Yes | D16: Included in iorta fee | E16: 0 | F16: 0 | G16: Included in iorta fee | H16: 0 | I16: 0 | J16: Open source; set up by iorta. IITH monitoring tools can be used instead.
A17: Commercial PostgreSQL support (EDB or similar) | B17: Annual | C17: Optional | D17: IIFT procures | E17: 5000 | F17: 10000 | G17: Not required | H17: 0 | I17: 0 | J17: Optional. Database support is already part of the AMC; vendor support only if IIFT policy requires it. Under Option B the managed database is supported by the cloud provider.
A18: Red Hat Enterprise Linux subscriptions | B18: Annual, per VM | C18: Optional | D18: IIFT procures | E18: 4500 | F18: 10800 | G18: Not required | H18: 0 | I18: 0 | J18: Optional. Ubuntu Server 24.04 LTS carries no licence fee; RHEL about B$500–1,200 per VM a year if IIFT standardises on it.
... A21: Payment gateway | B21: – | C21: Optional | D21: Not required | E21: 0 | F21: 0 | G21: Not required | H21: 0 | I21: 0 | J21: Not required: payments are recorded and verified in the back-office. Can be added later.
A22: Total required items, per year | E22: =SUM(E7:E16) | F22: =SUM(F7:F16) | H22: =SUM(H7:H16) | I22: =SUM(I7:I16)
A23: Total optional items, per year | E23: =SUM(E17:E21) | F23: =SUM(F17:F21) | H23: =SUM(H17:H21) | I23: =SUM(I17:I21)

Sheet Assumptions
A1: Assumptions and notes
A2: iorta TechNXT – proposal to Insurans Islam Family Takaful Sendirian Berhad – October 2026
A4: # | B4: Assumption
A5: 1 | B5: Option A sizing is taken from the Solution Architecture (Infrastructure Sizing) and is checked automatically against it when the BOM is built.
A6: 2 | B6: Indicative infrastructure costs assume new virtual capacity and storage on the IITH platform; reuse of existing capacity reduces them. Physical hardware, if required, is quoted by IIFT's suppliers.
A7: 3 | B7: Ubuntu Server 24.04 LTS is the baseline operating system (no licence fee); RHEL 9 is supported if IIFT prefers it, at IIFT's cost.
A8: 4 | B8: SMS volume of about 6,000 messages a year (OTP and alerts) at B$0.05–0.10 per message.
A9: 5 | B9: AML screening reuses IIFT's existing service or lists where possible; a new subscription is priced by the provider.
A10: 6 | B10: Cloud estimates use public list prices for the Malaysia region converted at USD 1 = B$ 1.30; actual charges vary with usage and exchange rates.
A11: 7 | B11: Escrow is an alternative to Option C (source code handover); agent fees are paid by IIFT.
A12: 8 | B12: All amounts exclude iorta's fees, which are in the pricing workbook.
