Workbook

Sheet Read-me
A4: SalesVerse 2.0 – Test Cases
A5: iorta TechNXT – IIFT Agent/Banca Portal & Back-office for Insurans Islam Family Takaful Sendirian Berhad – October 2026
A7: Document reference | B7: IIFT-SV2-TCS
A8: RFP deliverables | B8: DEL-13 (test scenarios and expected results), DEL-14 precursor (execution evidence); UAT cases (DEL-15) are derived from the scenarios marked UAT
A9: Status as of | B9: 2 October 2026, source commit af2fb05
A10: Companion document | B10: SalesVerse-2.0-Test-Strategy (IIFT-SV2-TST): levels, environments, entry/exit criteria, schedule; its 'Status post testing' section is built from the same data as the Summary sheet
A11: Classification | B11: Commercial-in-Confidence
A13: How to read this workbook
A14: • Scenarios: one business or technical situation per row, traced to RFP identifiers (AP, BO, INT, COM, NFR, DEL, MNT, FFR) with persona, pre-conditions and expected end state.
A15: • Conditions: the rules and decisions inside each scenario that at least one case verifies (for example 'nominee shares must total 100%').
A16: • Cases: the executable cases with numbered steps, test data, expected result, level, automation, status, evidence and execution details. Filter by Area, Level or Status.
A17: • Defects: failures found during the run with severity and status (headers only when none).
A18: • Traceability: every RFP requirement in scope with its scenarios, case identifiers and coverage; requirements without a case are marked.
A19: • Execution log: every API case executed by the test run script, the automated suite re-runs and the security check run, with request, response and verdict.
A20: • Summary: counts by status, level, area and automation as formulas over the Cases sheet, with the catalogue's own count beside each for a drift check.
A22: Status and level definitions
A23: Term | B23: Meaning
A24: Passed | B24: Executed and the expected result observed (automated run, API run or manual exploratory run with a screen capture).
A25: Failed | B25: Executed and the expected result not observed; a defect reference is given.
A26: Blocked | B26: Execution attempted but a pre-condition was not available in the test data or environment.
A27: Not executed | B27: Not run in the iorta test environment; the Evidence column states why (IIFT environment, time-based job, UAT, VAPT, performance scale, not yet built).
A28: Unit | B28: Vitest unit tests of the API (business rules, rating engines, validators) and of web components (Testing Library).
A29: API | B29: System cases executed by tools/testing/api-test-run.mjs through the HTTP API of the running demonstration instance.
A30: E2E | B30: The end-to-end suite apps/api/test/*.e2e-spec.ts (supertest against a dedicated PostgreSQL test database).
A31: UI | B31: Manual exploratory runs in the browser; evidence is a screen capture in evidence/ui-screens.
A32: Security | B32: The OWASP Top 10 checks in tools/security/security-checks.mjs.
A33: SIT / Perf / UAT | B33: Levels that need IIFT's systems, scale or users; executed in weeks 16–22 of the plan.
A34: Automation | B34: 'Automated – <spec>' for tests in the repository; 'Executed – API run' for the scripted run; 'Manual (exploratory)'; 'Not automated'.
A36: Evidence files (docs/technical/evidence)
A37: File | B37: Content
A38: api-unit-tests.json | B38: Vitest results of the API unit tests (59)
A39: web-unit-tests.json | B39: Vitest results of the web unit tests at the evidence capture (81)
A40: api-e2e-tests.json | B40: Vitest results of the end-to-end suite (32)
A41: test-reruns.json | B41: Re-runs of the three suites by iorta QA on 2 October 2026 (59, 91 and 32 tests); the later result is the status shown
A42: security-checks.json | B42: 29 OWASP checks (see the Security Assessment Report)
A43: api-test-run.json | B43: API run of 113 cases: 111 passed, 2 not passed; started 2026-10-02 22:12 UTC
A44: ui-screens/ | B44: Screen captures cited by the manual cases (JPEG copies of the PNG captures)
A46: Conventions
A47: • Demonstration users: ag-000001 (agency principal), ag-000002 (sub-agent), ag-000003 (principal of another agency), bk-000004 and bk-000005 (bank officers; the bank is blocked for new business), manager, ops.maker, ops.checker, underwriter, finance, compliance, support, admin.
A48: • Dates in the execution log are UTC; the application's business day is the Brunei calendar day (UTC+8).
A49: • Cases are numbered CS-nnnn in area order; scenario and condition identifiers are stable keys used by the Test Strategy.
A50: • The workbook is generated by docs/technical/build/build_test_cases.py; edit the catalogue modules, not the file.

Sheet Summary
A4: SalesVerse 2.0 – Test status summary
A5: As of 2 October 2026 (commit af2fb05); formulas count the Cases sheet, 'Catalogue' is the generator's count
A7: Catalogue size
A8: Item | B8: Count | C8: Catalogue | D8: Check
A9: Test scenarios | B9: =COUNTA(Scenarios!A:A)-1 | C9: 70 | D9: =IF(B9=C9,"OK","DRIFT")
A10: Test conditions | B10: =COUNTA(Conditions!A:A)-1 | C10: 196 | D10: =IF(B10=C10,"OK","DRIFT")
A11: Test cases | B11: =COUNTA(Cases!A:A)-1 | C11: 438 | D11: =IF(B11=C11,"OK","DRIFT")
A13: Cases by status
A14: Status | B14: Cases | C14: Catalogue | D14: Check | E14: Share
A15: Status: Passed | B15: =COUNTIF(Cases!$L:$L,"Passed") | C15: 384 | D15: =IF(B15=C15,"OK","DRIFT") | E15: =B15/$B$19
A16: Status: Failed | B16: =COUNTIF(Cases!$L:$L,"Failed") | C16: 2 | D16: =IF(B16=C16,"OK","DRIFT") | E16: =B16/$B$19
A17: Status: Blocked | B17: =COUNTIF(Cases!$L:$L,"Blocked") | C17: 1 | D17: =IF(B17=C17,"OK","DRIFT") | E17: =B17/$B$19
A18: Status: Not executed | B18: =COUNTIF(Cases!$L:$L,"Not executed") | C18: 51 | D18: =IF(B18=C18,"OK","DRIFT") | E18: =B18/$B$19
A19: Total | B19: =SUM(B15:B18) | C19: =SUM(C15:C18) | D19: =IF(B19=C19,"OK","DRIFT") | E19: =B19/$B$19
A21: Cases by level
A22: Level | B22: Cases | C22: Passed | D22: Failed | E22: Blocked | F22: Not executed | G22: Catalogue | H22: Check
A23: Unit (API and web components) | B23: =COUNTIF(Cases!$J:$J,"Unit") | C23: =COUNTIFS(Cases!$J:$J,"Unit",Cases!$L:$L,"Passed") | D23: =COUNTIFS(Cases!$J:$J,"Unit",Cases!$L:$L,"Failed") | E23: =COUNTIFS(Cases!$J:$J,"Unit",Cases!$L:$L,"Blocked") | F23: =COUNTIFS(Cases!$J:$J,"Unit",Cases!$L:$L,"Not executed") | G23: 150 | H23: =IF(B23=G23,"OK","DRIFT")
A24: API system cases executed against the running system | B24: =COUNTIF(Cases!$J:$J,"API") | C24: =COUNTIFS(Cases!$J:$J,"API",Cases!$L:$L,"Passed") | D24: =COUNTIFS(Cases!$J:$J,"API",Cases!$L:$L,"Failed") | E24: =COUNTIFS(Cases!$J:$J,"API",Cases!$L:$L,"Blocked") | F24: =COUNTIFS(Cases!$J:$J,"API",Cases!$L:$L,"Not executed") | G24: 122 | H24: =IF(B24=G24,"OK","DRIFT")
A25: End-to-end API suite (business journeys) | B25: =COUNTIF(Cases!$J:$J,"E2E") | C25: =COUNTIFS(Cases!$J:$J,"E2E",Cases!$L:$L,"Passed") | D25: =COUNTIFS(Cases!$J:$J,"E2E",Cases!$L:$L,"Failed") | E25: =COUNTIFS(Cases!$J:$J,"E2E",Cases!$L:$L,"Blocked") | F25: =COUNTIFS(Cases!$J:$J,"E2E",Cases!$L:$L,"Not executed") | G25: 44 | H25: =IF(B25=G25,"OK","DRIFT")
A26: User interface (manual, exploratory) | B26: =COUNTIF(Cases!$J:$J,"UI") | C26: =COUNTIFS(Cases!$J:$J,"UI",Cases!$L:$L,"Passed") | D26: =COUNTIFS(Cases!$J:$J,"UI",Cases!$L:$L,"Failed") | E26: =COUNTIFS(Cases!$J:$J,"UI",Cases!$L:$L,"Blocked") | F26: =COUNTIFS(Cases!$J:$J,"UI",Cases!$L:$L,"Not executed") | G26: 57 | H26: =IF(B26=G26,"OK","DRIFT")
A27: Security checks (OWASP Top 10) | B27: =COUNTIF(Cases!$J:$J,"Security") | C27: =COUNTIFS(Cases!$J:$J,"Security",Cases!$L:$L,"Passed") | D27: =COUNTIFS(Cases!$J:$J,"Security",Cases!$L:$L,"Failed") | E27: =COUNTIFS(Cases!$J:$J,"Security",Cases!$L:$L,"Blocked") | F27: =COUNTIFS(Cases!$J:$J,"Security",Cases!$L:$L,"Not executed") | G27: 34 | H27: =IF(B27=G27,"OK","DRIFT")
A28: System integration test with IIFT systems | B28: =COUNTIF(Cases!$J:$J,"SIT") | C28: =COUNTIFS(Cases!$J:$J,"SIT",Cases!$L:$L,"Passed") | D28: =COUNTIFS(Cases!$J:$J,"SIT",Cases!$L:$L,"Failed") | E28: =COUNTIFS(Cases!$J:$J,"SIT",Cases!$L:$L,"Blocked") | F28: =COUNTIFS(Cases!$J:$J,"SIT",Cases!$L:$L,"Not executed") | G28: 25 | H28: =IF(B28=G28,"OK","DRIFT")
A29: Performance | B29: =COUNTIF(Cases!$J:$J,"Perf") | C29: =COUNTIFS(Cases!$J:$J,"Perf",Cases!$L:$L,"Passed") | D29: =COUNTIFS(Cases!$J:$J,"Perf",Cases!$L:$L,"Failed") | E29: =COUNTIFS(Cases!$J:$J,"Perf",Cases!$L:$L,"Blocked") | F29: =COUNTIFS(Cases!$J:$J,"Perf",Cases!$L:$L,"Not executed") | G29: 3 | H29: =IF(B29=G29,"OK","DRIFT")
A30: User acceptance | B30: =COUNTIF(Cases!$J:$J,"UAT") | C30: =COUNTIFS(Cases!$J:$J,"UAT",Cases!$L:$L,"Passed") | D30: =COUNTIFS(Cases!$J:$J,"UAT",Cases!$L:$L,"Failed") | E30: =COUNTIFS(Cases!$J:$J,"UAT",Cases!$L:$L,"Blocked") | F30: =COUNTIFS(Cases!$J:$J,"UAT",Cases!$L:$L,"Not executed") | G30: 3 | H30: =IF(B30=G30,"OK","DRIFT")
A31: Total | B31: =SUM(B23:B30) | C31: =SUM(C23:C30) | D31: =SUM(D23:D30) | E31: =SUM(E23:E30) | F31: =SUM(F23:F30) | G31: =SUM(G23:G30) | H31: =IF(B31=G31,"OK","DRIFT")
A33: Cases by RFP area
A34: Area | B34: Cases | C34: Passed | D34: Failed | E34: Blocked | F34: Not executed | G34: Catalogue | H34: Check
A35: AUT – Authentication and session | B35: =COUNTIF(Cases!$D:$D,"AUT") | C35: =COUNTIFS(Cases!$D:$D,"AUT",Cases!$L:$L,"Passed") | D35: =COUNTIFS(Cases!$D:$D,"AUT",Cases!$L:$L,"Failed") | E35: =COUNTIFS(Cases!$D:$D,"AUT",Cases!$L:$L,"Blocked") | F35: =COUNTIFS(Cases!$D:$D,"AUT",Cases!$L:$L,"Not executed") | G35: 37 | H35: =IF(B35=G35,"OK","DRIFT")
A36: ACC – Access control and data scoping | B36: =COUNTIF(Cases!$D:$D,"ACC") | C36: =COUNTIFS(Cases!$D:$D,"ACC",Cases!$L:$L,"Passed") | D36: =COUNTIFS(Cases!$D:$D,"ACC",Cases!$L:$L,"Failed") | E36: =COUNTIFS(Cases!$D:$D,"ACC",Cases!$L:$L,"Blocked") | F36: =COUNTIFS(Cases!$D:$D,"ACC",Cases!$L:$L,"Not executed") | G36: 15 | H36: =IF(B36=G36,"OK","DRIFT")
A37: AGT – Agent and agency management | B37: =COUNTIF(Cases!$D:$D,"AGT") | C37: =COUNTIFS(Cases!$D:$D,"AGT",Cases!$L:$L,"Passed") | D37: =COUNTIFS(Cases!$D:$D,"AGT",Cases!$L:$L,"Failed") | E37: =COUNTIFS(Cases!$D:$D,"AGT",Cases!$L:$L,"Blocked") | F37: =COUNTIFS(Cases!$D:$D,"AGT",Cases!$L:$L,"Not executed") | G37: 18 | H37: =IF(B37=G37,"OK","DRIFT")
A38: PAR – Participant management | B38: =COUNTIF(Cases!$D:$D,"PAR") | C38: =COUNTIFS(Cases!$D:$D,"PAR",Cases!$L:$L,"Passed") | D38: =COUNTIFS(Cases!$D:$D,"PAR",Cases!$L:$L,"Failed") | E38: =COUNTIFS(Cases!$D:$D,"PAR",Cases!$L:$L,"Blocked") | F38: =COUNTIFS(Cases!$D:$D,"PAR",Cases!$L:$L,"Not executed") | G38: 11 | H38: =IF(B38=G38,"OK","DRIFT")
A39: AML – AML/KYC screening | B39: =COUNTIF(Cases!$D:$D,"AML") | C39: =COUNTIFS(Cases!$D:$D,"AML",Cases!$L:$L,"Passed") | D39: =COUNTIFS(Cases!$D:$D,"AML",Cases!$L:$L,"Failed") | E39: =COUNTIFS(Cases!$D:$D,"AML",Cases!$L:$L,"Blocked") | F39: =COUNTIFS(Cases!$D:$D,"AML",Cases!$L:$L,"Not executed") | G39: 14 | H39: =IF(B39=G39,"OK","DRIFT")
A40: PRD – Products and rating | B40: =COUNTIF(Cases!$D:$D,"PRD") | C40: =COUNTIFS(Cases!$D:$D,"PRD",Cases!$L:$L,"Passed") | D40: =COUNTIFS(Cases!$D:$D,"PRD",Cases!$L:$L,"Failed") | E40: =COUNTIFS(Cases!$D:$D,"PRD",Cases!$L:$L,"Blocked") | F40: =COUNTIFS(Cases!$D:$D,"PRD",Cases!$L:$L,"Not executed") | G40: 36 | H40: =IF(B40=G40,"OK","DRIFT")
A41: QUO – Quotation and submission | B41: =COUNTIF(Cases!$D:$D,"QUO") | C41: =COUNTIFS(Cases!$D:$D,"QUO",Cases!$L:$L,"Passed") | D41: =COUNTIFS(Cases!$D:$D,"QUO",Cases!$L:$L,"Failed") | E41: =COUNTIFS(Cases!$D:$D,"QUO",Cases!$L:$L,"Blocked") | F41: =COUNTIFS(Cases!$D:$D,"QUO",Cases!$L:$L,"Not executed") | G41: 31 | H41: =IF(B41=G41,"OK","DRIFT")
A42: WFL – Approval workflow (maker-checker) | B42: =COUNTIF(Cases!$D:$D,"WFL") | C42: =COUNTIFS(Cases!$D:$D,"WFL",Cases!$L:$L,"Passed") | D42: =COUNTIFS(Cases!$D:$D,"WFL",Cases!$L:$L,"Failed") | E42: =COUNTIFS(Cases!$D:$D,"WFL",Cases!$L:$L,"Blocked") | F42: =COUNTIFS(Cases!$D:$D,"WFL",Cases!$L:$L,"Not executed") | G42: 10 | H42: =IF(B42=G42,"OK","DRIFT")
A43: POL – Policy issuance and policy documents | B43: =COUNTIF(Cases!$D:$D,"POL") | C43: =COUNTIFS(Cases!$D:$D,"POL",Cases!$L:$L,"Passed") | D43: =COUNTIFS(Cases!$D:$D,"POL",Cases!$L:$L,"Failed") | E43: =COUNTIFS(Cases!$D:$D,"POL",Cases!$L:$L,"Blocked") | F43: =COUNTIFS(Cases!$D:$D,"POL",Cases!$L:$L,"Not executed") | G43: 12 | H43: =IF(B43=G43,"OK","DRIFT")
A44: BIL – Billing and payments | B44: =COUNTIF(Cases!$D:$D,"BIL") | C44: =COUNTIFS(Cases!$D:$D,"BIL",Cases!$L:$L,"Passed") | D44: =COUNTIFS(Cases!$D:$D,"BIL",Cases!$L:$L,"Failed") | E44: =COUNTIFS(Cases!$D:$D,"BIL",Cases!$L:$L,"Blocked") | F44: =COUNTIFS(Cases!$D:$D,"BIL",Cases!$L:$L,"Not executed") | G44: 17 | H44: =IF(B44=G44,"OK","DRIFT")
A45: SVC – Policy servicing: renewal, endorsement, cancellation | B45: =COUNTIF(Cases!$D:$D,"SVC") | C45: =COUNTIFS(Cases!$D:$D,"SVC",Cases!$L:$L,"Passed") | D45: =COUNTIFS(Cases!$D:$D,"SVC",Cases!$L:$L,"Failed") | E45: =COUNTIFS(Cases!$D:$D,"SVC",Cases!$L:$L,"Blocked") | F45: =COUNTIFS(Cases!$D:$D,"SVC",Cases!$L:$L,"Not executed") | G45: 10 | H45: =IF(B45=G45,"OK","DRIFT")
A46: CLM – Claims notification | B46: =COUNTIF(Cases!$D:$D,"CLM") | C46: =COUNTIFS(Cases!$D:$D,"CLM",Cases!$L:$L,"Passed") | D46: =COUNTIFS(Cases!$D:$D,"CLM",Cases!$L:$L,"Failed") | E46: =COUNTIFS(Cases!$D:$D,"CLM",Cases!$L:$L,"Blocked") | F46: =COUNTIFS(Cases!$D:$D,"CLM",Cases!$L:$L,"Not executed") | G46: 5 | H46: =IF(B46=G46,"OK","DRIFT")
A47: DOC – Documents and uploads | B47: =COUNTIF(Cases!$D:$D,"DOC") | C47: =COUNTIFS(Cases!$D:$D,"DOC",Cases!$L:$L,"Passed") | D47: =COUNTIFS(Cases!$D:$D,"DOC",Cases!$L:$L,"Failed") | E47: =COUNTIFS(Cases!$D:$D,"DOC",Cases!$L:$L,"Blocked") | F47: =COUNTIFS(Cases!$D:$D,"DOC",Cases!$L:$L,"Not executed") | G47: 14 | H47: =IF(B47=G47,"OK","DRIFT")
A48: DSH – Dashboards and notifications | B48: =COUNTIF(Cases!$D:$D,"DSH") | C48: =COUNTIFS(Cases!$D:$D,"DSH",Cases!$L:$L,"Passed") | D48: =COUNTIFS(Cases!$D:$D,"DSH",Cases!$L:$L,"Failed") | E48: =COUNTIFS(Cases!$D:$D,"DSH",Cases!$L:$L,"Blocked") | F48: =COUNTIFS(Cases!$D:$D,"DSH",Cases!$L:$L,"Not executed") | G48: 8 | H48: =IF(B48=G48,"OK","DRIFT")
A49: ISS – Issue management and SLA | B49: =COUNTIF(Cases!$D:$D,"ISS") | C49: =COUNTIFS(Cases!$D:$D,"ISS",Cases!$L:$L,"Passed") | D49: =COUNTIFS(Cases!$D:$D,"ISS",Cases!$L:$L,"Failed") | E49: =COUNTIFS(Cases!$D:$D,"ISS",Cases!$L:$L,"Blocked") | F49: =COUNTIFS(Cases!$D:$D,"ISS",Cases!$L:$L,"Not executed") | G49: 9 | H49: =IF(B49=G49,"OK","DRIFT")
A50: RPT – Reporting | B50: =COUNTIF(Cases!$D:$D,"RPT") | C50: =COUNTIFS(Cases!$D:$D,"RPT",Cases!$L:$L,"Passed") | D50: =COUNTIFS(Cases!$D:$D,"RPT",Cases!$L:$L,"Failed") | E50: =COUNTIFS(Cases!$D:$D,"RPT",Cases!$L:$L,"Blocked") | F50: =COUNTIFS(Cases!$D:$D,"RPT",Cases!$L:$L,"Not executed") | G50: 13 | H50: =IF(B50=G50,"OK","DRIFT")
A51: AUD – Audit trail | B51: =COUNTIF(Cases!$D:$D,"AUD") | C51: =COUNTIFS(Cases!$D:$D,"AUD",Cases!$L:$L,"Passed") | D51: =COUNTIFS(Cases!$D:$D,"AUD",Cases!$L:$L,"Failed") | E51: =COUNTIFS(Cases!$D:$D,"AUD",Cases!$L:$L,"Blocked") | F51: =COUNTIFS(Cases!$D:$D,"AUD",Cases!$L:$L,"Not executed") | G51: 3 | H51: =IF(B51=G51,"OK","DRIFT")
A52: ADM – Administration and configuration | B52: =COUNTIF(Cases!$D:$D,"ADM") | C52: =COUNTIFS(Cases!$D:$D,"ADM",Cases!$L:$L,"Passed") | D52: =COUNTIFS(Cases!$D:$D,"ADM",Cases!$L:$L,"Failed") | E52: =COUNTIFS(Cases!$D:$D,"ADM",Cases!$L:$L,"Blocked") | F52: =COUNTIFS(Cases!$D:$D,"ADM",Cases!$L:$L,"Not executed") | G52: 13 | H52: =IF(B52=G52,"OK","DRIFT")
A53: INT – Integration and end-of-day | B53: =COUNTIF(Cases!$D:$D,"INT") | C53: =COUNTIFS(Cases!$D:$D,"INT",Cases!$L:$L,"Passed") | D53: =COUNTIFS(Cases!$D:$D,"INT",Cases!$L:$L,"Failed") | E53: =COUNTIFS(Cases!$D:$D,"INT",Cases!$L:$L,"Blocked") | F53: =COUNTIFS(Cases!$D:$D,"INT",Cases!$L:$L,"Not executed") | G53: 19 | H53: =IF(B53=G53,"OK","DRIFT")
A54: SEC – Application security | B54: =COUNTIF(Cases!$D:$D,"SEC") | C54: =COUNTIFS(Cases!$D:$D,"SEC",Cases!$L:$L,"Passed") | D54: =COUNTIFS(Cases!$D:$D,"SEC",Cases!$L:$L,"Failed") | E54: =COUNTIFS(Cases!$D:$D,"SEC",Cases!$L:$L,"Blocked") | F54: =COUNTIFS(Cases!$D:$D,"SEC",Cases!$L:$L,"Not executed") | G54: 25 | H54: =IF(B54=G54,"OK","DRIFT")
A55: NFR – Non-functional: performance, availability, DR, usability | B55: =COUNTIF(Cases!$D:$D,"NFR") | C55: =COUNTIFS(Cases!$D:$D,"NFR",Cases!$L:$L,"Passed") | D55: =COUNTIFS(Cases!$D:$D,"NFR",Cases!$L:$L,"Failed") | E55: =COUNTIFS(Cases!$D:$D,"NFR",Cases!$L:$L,"Blocked") | F55: =COUNTIFS(Cases!$D:$D,"NFR",Cases!$L:$L,"Not executed") | G55: 17 | H55: =IF(B55=G55,"OK","DRIFT")
A56: PLT – Platform behaviour and configuration | B56: =COUNTIF(Cases!$D:$D,"PLT") | C56: =COUNTIFS(Cases!$D:$D,"PLT",Cases!$L:$L,"Passed") | D56: =COUNTIFS(Cases!$D:$D,"PLT",Cases!$L:$L,"Failed") | E56: =COUNTIFS(Cases!$D:$D,"PLT",Cases!$L:$L,"Blocked") | F56: =COUNTIFS(Cases!$D:$D,"PLT",Cases!$L:$L,"Not executed") | G56: 101 | H56: =IF(B56=G56,"OK","DRIFT")
A57: Total | B57: =SUM(B35:B56) | C57: =SUM(C35:C56) | D57: =SUM(D35:D56) | E57: =SUM(E35:E56) | F57: =SUM(F35:F56) | G57: =SUM(G35:G56) | H57: =IF(B57=G57,"OK","DRIFT")
A59: Cases by automation
A60: Automation | B60: Cases | C60: Catalogue | D60: Check
A61: Automated | B61: =COUNTIF(Cases!$K:$K,"Automated*") | C61: 223 | D61: =IF(B61=C61,"OK","DRIFT")
A62: Executed – API run | B62: =COUNTIF(Cases!$K:$K,"Executed*") | C62: 113 | D62: =IF(B62=C62,"OK","DRIFT")
A63: Manual | B63: =COUNTIF(Cases!$K:$K,"Manual*") | C63: 51 | D63: =IF(B63=C63,"OK","DRIFT")
A64: Not automated | B64: =COUNTIF(Cases!$K:$K,"Not automated") | C64: 51 | D64: =IF(B64=C64,"OK","DRIFT")
A66: Defects
A67: Item | B67: Count | C67: Catalogue | D67: Check
A68: Defects recorded | B68: =COUNTA(Defects!A:A)-1 | C68: 2 | D68: =IF(B68=C68,"OK","DRIFT")
A69: Cases with a defect reference | B69: =COUNTIF(Cases!$P:$P,"DEF-*") | C69: 2 | D69: =IF(B69=C69,"OK","DRIFT")

Sheet Scenarios
A1: ID | B1: Area | C1: RFP IDs | D1: Persona | E1: Scenario | F1: Pre-conditions | G1: Expected end state | H1: Conditions | I1: Cases
A2: TS-01 | B2: AUT – Authentication and session | C2: AP-01, BO-01, NFR-09 | D2: Agent, bank officer, staff | E2: Sign in with a user name and password; wrong credentials are refused without revealing which part was wrong. | F2: Demonstration users loaded; account active. | G2: Session established; failed attempts recorded in the audit trail. | H2: =COUNTIF(Conditions!$B:$B,A2) | I2: =COUNTIF(Cases!$B:$B,A2)
A3: TS-02 | B3: AUT – Authentication and session | C3: AP-02, NFR-09 | D3: Any user, administrator | E3: Change a password under the configurable policy (length, character classes, history, expiry, no user name); temporary passwords must be changed at first sign-in. | F3: Signed in; password parameters at defaults. | G3: Password changed; other sessions ended; policy breaches refused. | H3: =COUNTIF(Conditions!$B:$B,A3) | I3: =COUNTIF(Cases!$B:$B,A3)
A4: TS-03 | B4: AUT – Authentication and session | C4: AP-03, NFR-09 | D4: Any user | E4: Session management: cookie flags, new session id at sign-in, logout revocation, single active session, idle and absolute timeout. | F4: Signed in. | G4: Old sessions unusable; timeouts applied from parameters. | H4: =COUNTIF(Conditions!$B:$B,A4) | I4: =COUNTIF(Cases!$B:$B,A4)
A5: TS-04 | B5: AUT – Authentication and session | C5: AP-04, NFR-09 | D5: Any user, administrator | E5: Account lockout after the configured failed attempts and administrator unlock. | F5: Lockout parameters at defaults (5 attempts, 30 minutes). | G5: Account locked then unlocked; events audited. | H5: =COUNTIF(Conditions!$B:$B,A5) | I5: =COUNTIF(Cases!$B:$B,A5)
A6: TS-05 | B6: AUT – Authentication and session | C6: INT-06, BO-01 | D6: Back-office staff | E6: Back-office sign-on through the corporate directory (LDAP/Active Directory) with escaped filters. | F6: LDAP configured (IIFT environment). | G6: Directory users sign in; local accounts unaffected. | H6: =COUNTIF(Conditions!$B:$B,A6) | I6: =COUNTIF(Cases!$B:$B,A6)
A7: TS-06 | B7: ACC – Access control and data scoping | C7: AP-59, BO-02, COM-02, NFR-10 | D7: All personas | E7: Role-based access: every route checks a permission; portal and back-office audiences are separate; roles grant least privilege. | F7: Demonstration roles loaded. | G7: Unauthorised calls refused with 401/403; authorised calls succeed. | H7: =COUNTIF(Conditions!$B:$B,A7) | I7: =COUNTIF(Cases!$B:$B,A7)
A8: TS-07 | B8: ACC – Access control and data scoping | C8: AP-09, AP-11, AP-12, AP-59, COM-02 | D8: Agents, bank officers, supervisors | E8: Data scoping: agents see their own and their sub-agents' records; principals and bank supervisors see the whole agency/bank; other agencies' records are not disclosed. | F8: Two agencies and one bank with business. | G8: Records outside the scope answer 404/403; participant profile shared only through exact-ID lookup. | H8: =COUNTIF(Conditions!$B:$B,A8) | I8: =COUNTIF(Cases!$B:$B,A8)
A9: TS-08 | B9: AGT – Agent and agency management | C9: AP-07, AP-08, AP-48, BO-10, BO-11 | D9: Agency principal, operations checker | E9: Online registration of a sub-agent with AML screening, document upload and maker-checker approval; agent code generated; portal account created. | F9: Principal signed in; checker available. | G9: Agent ACTIVE with a unique code and a user that must change its temporary password. | H9: =COUNTIF(Conditions!$B:$B,A9) | I9: =COUNTIF(Cases!$B:$B,A9)
A10: TS-09 | B10: AGT – Agent and agency management | C10: AP-05, AP-06, AP-09, AP-10, BO-08 | D10: Agent, bank officer | E10: Profile, agency information and hierarchy views; profile changes submitted for approval and withdrawable by the maker. | F10: Signed in as a sub-agent. | G10: Profile request pending or withdrawn; hierarchy shows the reporting line. | H10: =COUNTIF(Conditions!$B:$B,A10) | I10: =COUNTIF(Cases!$B:$B,A10)
A11: TS-10 | B11: AGT – Agent and agency management | C11: BO-05, BO-06, BO-07, BO-08, BO-09 | D11: Operations maker/checker, manager | E11: Back-office agent and agency administration: search, status changes with allowed transitions, agency creation and maintenance, payment-block lift. | F11: Back-office user with the relevant permissions. | G11: Changes applied after approval; invalid transitions refused. | H11: =COUNTIF(Conditions!$B:$B,A11) | I11: =COUNTIF(Cases!$B:$B,A11)
A12: TS-11 | B12: PAR – Participant management | C12: AP-13, AP-14, AP-15, AP-48, NFR-30 | D12: Agent, operations checker | E12: Register individual and corporate participants with validation, search them, and submit profile updates for approval. | F12: Signed in as an agent. | G12: Participant number assigned; updates applied after approval. | H12: =COUNTIF(Conditions!$B:$B,A12) | I12: =COUNTIF(Cases!$B:$B,A12)
A13: TS-12 | B13: PAR – Participant management | C13: AP-11, AP-12, COM-01 | D13: Agents of different agencies | E13: Single shared participant profile: duplicate identification numbers refused, exact-ID lookup across agencies returns a masked summary, full profile visible once business exists. | F13: Participant registered by agency A. | G13: No duplicate profiles; cross-agency visibility limited as designed. | H13: =COUNTIF(Conditions!$B:$B,A13) | I13: =COUNTIF(Cases!$B:$B,A13)
... A71: TS-70 | B71: PLT – Platform behaviour and configuration | C71: NFR-22 | D71: Developer, QA | E71: Web application components: API client (CSRF, session end), formatting, status display, navigation, permission gating, forms. | F71: Unit test environment. | G71: Components behave per specification. | H71: =COUNTIF(Conditions!$B:$B,A71) | I71: =COUNTIF(Cases!$B:$B,A71)

Sheet Conditions
A1: ID | B1: Scenario | C1: Area | D1: Condition / rule under test | E1: Cases | F1: Passed | G1: Failed | H1: Blocked | I1: Not executed
A2: TC-001 | B2: TS-01 | C2: AUT – Authentication and session | D2: Unknown user and wrong password return the same message and code INVALID_CREDENTIALS | E2: =COUNTIF(Cases!$C:$C,A2) | F2: =COUNTIFS(Cases!$C:$C,A2,Cases!$L:$L,"Passed") | G2: =COUNTIFS(Cases!$C:$C,A2,Cases!$L:$L,"Failed") | H2: =COUNTIFS(Cases!$C:$C,A2,Cases!$L:$L,"Blocked") | I2: =COUNTIFS(Cases!$C:$C,A2,Cases!$L:$L,"Not executed")
A3: TC-002 | B3: TS-01 | C3: AUT – Authentication and session | D3: Successful sign-in returns the user profile, permissions and a CSRF token; never a password hash | E3: =COUNTIF(Cases!$C:$C,A3) | F3: =COUNTIFS(Cases!$C:$C,A3,Cases!$L:$L,"Passed") | G3: =COUNTIFS(Cases!$C:$C,A3,Cases!$L:$L,"Failed") | H3: =COUNTIFS(Cases!$C:$C,A3,Cases!$L:$L,"Blocked") | I3: =COUNTIFS(Cases!$C:$C,A3,Cases!$L:$L,"Not executed")
A4: TC-003 | B4: TS-01 | C4: AUT – Authentication and session | D4: Failed sign-ins are recorded in the audit trail with the client IP address | E4: =COUNTIF(Cases!$C:$C,A4) | F4: =COUNTIFS(Cases!$C:$C,A4,Cases!$L:$L,"Passed") | G4: =COUNTIFS(Cases!$C:$C,A4,Cases!$L:$L,"Failed") | H4: =COUNTIFS(Cases!$C:$C,A4,Cases!$L:$L,"Blocked") | I4: =COUNTIFS(Cases!$C:$C,A4,Cases!$L:$L,"Not executed")
A5: TC-004 | B5: TS-01 | C5: AUT – Authentication and session | D5: Sign-in attempts are rate limited per client address (HTTP 429) | E5: =COUNTIF(Cases!$C:$C,A5) | F5: =COUNTIFS(Cases!$C:$C,A5,Cases!$L:$L,"Passed") | G5: =COUNTIFS(Cases!$C:$C,A5,Cases!$L:$L,"Failed") | H5: =COUNTIFS(Cases!$C:$C,A5,Cases!$L:$L,"Blocked") | I5: =COUNTIFS(Cases!$C:$C,A5,Cases!$L:$L,"Not executed")
A6: TC-005 | B6: TS-01 | C6: AUT – Authentication and session | D6: Injection payloads in sign-in fields are rejected as invalid credentials | E6: =COUNTIF(Cases!$C:$C,A6) | F6: =COUNTIFS(Cases!$C:$C,A6,Cases!$L:$L,"Passed") | G6: =COUNTIFS(Cases!$C:$C,A6,Cases!$L:$L,"Failed") | H6: =COUNTIFS(Cases!$C:$C,A6,Cases!$L:$L,"Blocked") | I6: =COUNTIFS(Cases!$C:$C,A6,Cases!$L:$L,"Not executed")
A7: TC-006 | B7: TS-01 | C7: AUT – Authentication and session | D7: Sign-in page validates both fields and shows the server's error message | E7: =COUNTIF(Cases!$C:$C,A7) | F7: =COUNTIFS(Cases!$C:$C,A7,Cases!$L:$L,"Passed") | G7: =COUNTIFS(Cases!$C:$C,A7,Cases!$L:$L,"Failed") | H7: =COUNTIFS(Cases!$C:$C,A7,Cases!$L:$L,"Blocked") | I7: =COUNTIFS(Cases!$C:$C,A7,Cases!$L:$L,"Not executed")
A8: TC-007 | B8: TS-02 | C8: AUT – Authentication and session | D8: Password must meet the configured length and character-class rules and must not contain the user name | E8: =COUNTIF(Cases!$C:$C,A8) | F8: =COUNTIFS(Cases!$C:$C,A8,Cases!$L:$L,"Passed") | G8: =COUNTIFS(Cases!$C:$C,A8,Cases!$L:$L,"Failed") | H8: =COUNTIFS(Cases!$C:$C,A8,Cases!$L:$L,"Blocked") | I8: =COUNTIFS(Cases!$C:$C,A8,Cases!$L:$L,"Not executed")
A9: TC-008 | B9: TS-02 | C9: AUT – Authentication and session | D9: Last N passwords cannot be reused and passwords expire after the configured days | E9: =COUNTIF(Cases!$C:$C,A9) | F9: =COUNTIFS(Cases!$C:$C,A9,Cases!$L:$L,"Passed") | G9: =COUNTIFS(Cases!$C:$C,A9,Cases!$L:$L,"Failed") | H9: =COUNTIFS(Cases!$C:$C,A9,Cases!$L:$L,"Blocked") | I9: =COUNTIFS(Cases!$C:$C,A9,Cases!$L:$L,"Not executed")
A10: TC-009 | B10: TS-02 | C10: AUT – Authentication and session | D10: Passwords are hashed with Argon2id; current password must be given to change it | E10: =COUNTIF(Cases!$C:$C,A10) | F10: =COUNTIFS(Cases!$C:$C,A10,Cases!$L:$L,"Passed") | G10: =COUNTIFS(Cases!$C:$C,A10,Cases!$L:$L,"Failed") | H10: =COUNTIFS(Cases!$C:$C,A10,Cases!$L:$L,"Blocked") | I10: =COUNTIFS(Cases!$C:$C,A10,Cases!$L:$L,"Not executed")
A11: TC-010 | B11: TS-02 | C11: AUT – Authentication and session | D11: A temporary password must be changed before any other request succeeds (PASSWORD_CHANGE_REQUIRED) | E11: =COUNTIF(Cases!$C:$C,A11) | F11: =COUNTIFS(Cases!$C:$C,A11,Cases!$L:$L,"Passed") | G11: =COUNTIFS(Cases!$C:$C,A11,Cases!$L:$L,"Failed") | H11: =COUNTIFS(Cases!$C:$C,A11,Cases!$L:$L,"Blocked") | I11: =COUNTIFS(Cases!$C:$C,A11,Cases!$L:$L,"Not executed")
A12: TC-011 | B12: TS-02 | C12: AUT – Authentication and session | D12: Generated temporary passwords satisfy the policy | E12: =COUNTIF(Cases!$C:$C,A12) | F12: =COUNTIFS(Cases!$C:$C,A12,Cases!$L:$L,"Passed") | G12: =COUNTIFS(Cases!$C:$C,A12,Cases!$L:$L,"Failed") | H12: =COUNTIFS(Cases!$C:$C,A12,Cases!$L:$L,"Blocked") | I12: =COUNTIFS(Cases!$C:$C,A12,Cases!$L:$L,"Not executed")
A13: TC-012 | B13: TS-03 | C13: AUT – Authentication and session | D13: Session cookie is HttpOnly and SameSite=Strict; Secure in production | E13: =COUNTIF(Cases!$C:$C,A13) | F13: =COUNTIFS(Cases!$C:$C,A13,Cases!$L:$L,"Passed") | G13: =COUNTIFS(Cases!$C:$C,A13,Cases!$L:$L,"Failed") | H13: =COUNTIFS(Cases!$C:$C,A13,Cases!$L:$L,"Blocked") | I13: =COUNTIFS(Cases!$C:$C,A13,Cases!$L:$L,"Not executed")
... A197: TC-196 | B197: TS-70 | C197: PLT – Platform behaviour and configuration | D197: Sign-in page behaviour | E197: =COUNTIF(Cases!$C:$C,A197) | F197: =COUNTIFS(Cases!$C:$C,A197,Cases!$L:$L,"Passed") | G197: =COUNTIFS(Cases!$C:$C,A197,Cases!$L:$L,"Failed") | H197: =COUNTIFS(Cases!$C:$C,A197,Cases!$L:$L,"Blocked") | I197: =COUNTIFS(Cases!$C:$C,A197,Cases!$L:$L,"Not executed")

Sheet Cases
A1: ID | B1: Scenario | C1: Condition | D1: Area | E1: Title | F1: Persona / user | G1: Steps | H1: Test data | I1: Expected result | J1: Level | K1: Automation | L1: Status | M1: Evidence | N1: Executed on | O1: Executed by | P1: Defect ref
A2: CS-0001 | B2: TS-01 | C2: TC-001 | D2: AUT | E2: Wrong password and unknown user get the same generic 401 | F2: anonymous | G2: 1. POST /api/v1/auth/login with an unknown user name 2. POST /api/v1/auth/login as finance with a wrong password 3. Compare status, code and message | H2: username nobody-<run>; finance / wrong-password | I2: HTTP 401 INVALID_CREDENTIALS for both; identical message | J2: API | K2: Executed – API run (tools/testing/api-test-run.mjs) | L2: Passed | M2: api-test-run.json EX-001: POST /api/v1/auth/login (unknown user; finance with wrong password) → 401 INVALID_CREDENTIALS – Invalid username or password | 401 INVALID_CREDENTIALS – Invalid username or password | N2: 2 Oct 2026 22:12 UTC | O2: iorta TechNXT QA (API run)
A3: CS-0002 | B3: TS-01 | C3: TC-001 | D3: AUT | E3: Generic message for wrong credentials (suite) | F3: finance, support, ag-000001..3, admin | G3: 1. Run `npm run test:e2e -w apps/api` (rebuilds the iift_test database from the migrations and seeds) 2. Sign in as 'nobody' and as finance with a wrong password | H3: Unknown user; wrong password | I3: Both 401 INVALID_CREDENTIALS with identical message | J3: E2E | K3: Automated – apps/api/test/auth.e2e-spec.ts › rejects wrong credentials with a generic message | L3: Passed | M3: api-e2e-tests.json: 'Authentication and session security (AP-01..04, BO-01) rejects wrong credentials with a generic message' passed (2 Oct 2026 14:55 UTC); test-reruns.json: passed (2 Oct 2026 22:00 UTC) | N3: 2 Oct 2026 22:00 UTC | O3: iorta QA (Vitest e2e, iift_test database)
A4: CS-0003 | B4: TS-01 | C4: TC-001 | D4: AUT | E4: SEC-04 (OWASP A07): Same response for unknown user and wrong password (no user enumeration) | F4: Security tester | G4: 1. Run `node tools/security/security-checks.mjs` against a fresh non-production instance with demonstration data 2. Read the result of SEC-04 | H4: Demonstration users and records; crafted payloads as described in the script | I4: Identical message for unknown user and wrong password | J4: Security | K4: Automated – tools/security/security-checks.mjs | L4: Passed | M4: security-checks.json: SEC-04 PASS (2 Oct 2026 14:57 UTC); evidence summarised in the Security Assessment Report | N4: 2 Oct 2026 14:57 UTC | O4: iorta QA (security-checks.mjs)
A5: CS-0004 | B5: TS-01 | C5: TC-002 | D5: AUT | E5: Successful sign-in issues a HttpOnly SameSite=Strict cookie and a CSRF token | F5: ag-000001 | G5: 1. POST /api/v1/auth/login as ag-000001 2. Inspect Set-Cookie flags and the body | H5: ag-000001 / demo password | I5: HTTP 200; Set-Cookie has HttpOnly and SameSite=Strict; csrfToken present; no password hash in body | J5: API | K5: Executed – API run (tools/testing/api-test-run.mjs) | L5: Passed | M5: api-test-run.json EX-002: POST /api/v1/auth/login → 200; Set-Cookie flags: Path=/, HttpOnly, SameSite=Strict; csrfToken present | N5: 2 Oct 2026 22:12 UTC | O5: iorta TechNXT QA (API run)
A6: CS-0005 | B6: TS-01 | C6: TC-003 | D6: AUT | E6: SEC-27 (OWASP A09): Failed sign-ins are recorded in the audit trail with IP address | F6: Security tester | G6: 1. Run `node tools/security/security-checks.mjs` against a fresh non-production instance with demonstration data 2. Read the result of SEC-27 | H6: Demonstration users and records; crafted payloads as described in the script | I6: LOGIN_FAILED events with IP address in the audit trail | J6: Security | K6: Automated – tools/security/security-checks.mjs | L6: Passed | M6: security-checks.json: SEC-27 PASS (2 Oct 2026 14:57 UTC); evidence summarised in the Security Assessment Report | N6: 2 Oct 2026 14:57 UTC | O6: iorta QA (security-checks.mjs)
A7: CS-0006 | B7: TS-01 | C7: TC-004 | D7: AUT | E7: SEC-08 (OWASP A07): Sign-in attempts are rate limited per client (HTTP 429) | F7: Security tester | G7: 1. Run `node tools/security/security-checks.mjs` against a fresh non-production instance with demonstration data 2. Read the result of SEC-08 | H7: Demonstration users and records; crafted payloads as described in the script | I7: HTTP 429 once the per-client sign-in limit is reached | J7: Security | K7: Automated – tools/security/security-checks.mjs | L7: Passed | M7: security-checks.json: SEC-08 PASS (2 Oct 2026 14:57 UTC); evidence summarised in the Security Assessment Report | N7: 2 Oct 2026 14:57 UTC | O7: iorta QA (security-checks.mjs)
A8: CS-0007 | B8: TS-01 | C8: TC-004 | D8: AUT | E8: Sign-in rate limit per client address | F8: Anonymous | G8: 1. Send 11 sign-in attempts within a minute from one address | H8: LOGIN_RATE_LIMIT_PER_MINUTE = 10 | I8: Attempts after the tenth answer 429 | J8: Security | K8: Not automated | L8: Not executed | M8: Not executed in this run (would block the run's own sign-ins); covered by automated check SEC-08
A9: CS-0008 | B9: TS-01 | C9: TC-005 | D9: AUT | E9: SEC-18 (OWASP A03): Injection in sign-in fields is rejected as invalid credentials | F9: Security tester | G9: 1. Run `node tools/security/security-checks.mjs` against a fresh non-production instance with demonstration data 2. Read the result of SEC-18 | H9: Demonstration users and records; crafted payloads as described in the script | I9: 401 invalid credentials | J9: Security | K9: Automated – tools/security/security-checks.mjs | L9: Passed | M9: security-checks.json: SEC-18 PASS (2 Oct 2026 14:57 UTC); evidence summarised in the Security Assessment Report | N9: 2 Oct 2026 14:57 UTC | O9: iorta QA (security-checks.mjs)
A10: CS-0009 | B10: TS-01 | C10: TC-006 | D10: AUT | E10: Sign-in page at desktop and mobile widths | F10: ag-000001 | G10: 1. Open /login at 1440, 1280 and 390 px 2. Sign in | H10: Demo password | I10: Form usable at every width; dashboard opens | J10: UI | K10: Manual (exploratory) | L10: Passed | M10: Screens: ui-login-1440.png, ui-login-390.png, a-login.png (evidence/ui-screens) | N10: 2 Oct 2026 | O10: iorta QA (manual, exploratory)
A11: CS-0010 | B11: TS-02 | C11: TC-007 | D11: AUT | E11: PasswordService: accepts a password meeting every rule | F11: Developer / CI | G11: 1. Run `npm test -w apps/api` (Vitest) 2. Locate 'PasswordService accepts a password meeting every rule' in the run output | H11: Fixtures defined in modules/auth/password.service.spec.ts | I11: The test passes: PasswordService accepts a password meeting every rule. | J11: Unit | K11: Automated – modules/auth/password.service.spec.ts | L11: Passed | M11: api-unit-tests.json: 'PasswordService accepts a password meeting every rule' passed (2 Oct 2026 14:55 UTC); test-reruns.json: passed (2 Oct 2026 21:45 UTC) | N11: 2 Oct 2026 21:45 UTC | O11: iorta QA (Vitest)
A12: CS-0011 | B12: TS-02 | C12: TC-007 | D12: AUT | E12: PasswordService: rejects passwords containing the username | F12: Developer / CI | G12: 1. Run `npm test -w apps/api` (Vitest) 2. Locate 'PasswordService rejects passwords containing the username' in the run output | H12: Fixtures defined in modules/auth/password.service.spec.ts | I12: The test passes: PasswordService rejects passwords containing the username. | J12: Unit | K12: Automated – modules/auth/password.service.spec.ts | L12: Passed | M12: api-unit-tests.json: 'PasswordService rejects passwords containing the username' passed (2 Oct 2026 14:55 UTC); test-reruns.json: passed (2 Oct 2026 21:45 UTC) | N12: 2 Oct 2026 21:45 UTC | O12: iorta QA (Vitest)
A13: CS-0012 | B13: TS-02 | C13: TC-007 | D13: AUT | E13: PasswordService: reports every unmet rule together | F13: Developer / CI | G13: 1. Run `npm test -w apps/api` (Vitest) 2. Locate 'PasswordService reports every unmet rule together' in the run output | H13: Fixtures defined in modules/auth/password.service.spec.ts | I13: The test passes: PasswordService reports every unmet rule together. | J13: Unit | K13: Automated – modules/auth/password.service.spec.ts | L13: Passed | M13: api-unit-tests.json: 'PasswordService reports every unmet rule together' passed (2 Oct 2026 14:55 UTC); test-reruns.json: passed (2 Oct 2026 21:45 UTC) | N13: 2 Oct 2026 21:45 UTC | O13: iorta QA (Vitest)
A14: CS-0013 | B14: TS-02 | C14: TC-007 | D14: AUT | E14: Password policy is enforced on change-password | F14: ag-000002 | G14: 1. POST /api/v1/auth/change-password with newPassword 'password1' 2. POST with a wrong currentPassword 3. GET /api/v1/auth/me | H14: ag-000002 | I14: HTTP 422 PASSWORD_POLICY for a weak password; 422 CURRENT_PASSWORD_INCORRECT when the current password is wrong; the demo password is unchanged | J14: API | K14: Executed – API run (tools/testing/api-test-run.mjs) | L14: Passed | M14: api-test-run.json EX-006: POST /api/v1/auth/change-password (weak new password; wrong current password) → 422 PASSWORD_POLICY – Password does not meet the password policy [At least 12 characters; An upper-case letter; A symbol] | 422 CURRENT_PASSWORD_INCORRECT – Current password is incorrect | session still valid: 200 | N14: 2 Oct 2026 22:12 UTC | O14: iorta TechNXT QA (API run)
A15: CS-0014 | B15: TS-02 | C15: TC-008 | D15: AUT | E15: PasswordService: expires passwords after the configured number of days | F15: Developer / CI | G15: 1. Run `npm test -w apps/api` (Vitest) 2. Locate 'PasswordService expires passwords after the configured number of days' in the run output | H15: Fixtures defined in modules/auth/password.service.spec.ts | I15: The test passes: PasswordService expires passwords after the configured number of days. | J15: Unit | K15: Automated – modules/auth/password.service.spec.ts | L15: Passed | M15: api-unit-tests.json: 'PasswordService expires passwords after the configured number of days' passed (2 Oct 2026 14:55 UTC); test-reruns.json: passed (2 Oct 2026 21:45 UTC) | N15: 2 Oct 2026 21:45 UTC | O15: iorta QA (Vitest)
A16: CS-0015 | B16: TS-02 | C16: TC-008 | D16: AUT | E16: Password history and expiry | F16: Agent | G16: 1. Change password 6 times cycling back to the first 2. Set expiry to 1 day; sign in after | H16: history_count 5, expiry_days | I16: Reuse of the last 5 refused; expired password forces a change | J16: SIT | K16: Not automated | L16: Not executed | M16: Not executed – changes demonstration account passwords; run in SIT with dedicated accounts
A17: CS-0016 | B17: TS-02 | C17: TC-009 | D17: AUT | E17: PasswordService: hashes with Argon2id and verifies | F17: Developer / CI | G17: 1. Run `npm test -w apps/api` (Vitest) 2. Locate 'PasswordService hashes with Argon2id and verifies' in the run output | H17: Fixtures defined in modules/auth/password.service.spec.ts | I17: The test passes: PasswordService hashes with Argon2id and verifies. | J17: Unit | K17: Automated – modules/auth/password.service.spec.ts | L17: Passed | M17: api-unit-tests.json: 'PasswordService hashes with Argon2id and verifies' passed (2 Oct 2026 14:55 UTC); test-reruns.json: passed (2 Oct 2026 21:45 UTC) | N17: 2 Oct 2026 21:45 UTC | O17: iorta QA (Vitest)
A18: CS-0017 | B18: TS-02 | C18: TC-010 | D18: AUT | E18: Temporary password must be changed first; weak passwords refused (suite) | F18: finance, support, ag-000001..3, admin | G18: 1. Run `npm run test:e2e -w apps/api` (rebuilds the iift_test database from the migrations and seeds) 2. Sign in as admin with the seeded temporary password 3. GET /backoffice/users 4. Change to 'password1' 5. Change to a strong password 6. GET /backoffice/users | H18: admin / Temp#Admin2026x | I18: 403 PASSWORD_CHANGE_REQUIRED; 422 PASSWORD_POLICY; 200; 200 | J18: E2E | K18: Automated – apps/api/test/auth.e2e-spec.ts › forces a temporary password to be changed before anything else | L18: Passed | M18: api-e2e-tests.json: 'Authentication and session security (AP-01..04, BO-01) forces a temporary password to be changed before anything else' passed (2 Oct 2026 14:55 UTC); test-reruns.json: passed (2 Oct 2026 22:00 UTC) | N18: 2 Oct 2026 22:00 UTC | O18: iorta QA (Vitest e2e, iift_test database)
A19: CS-0018 | B19: TS-02 | C19: TC-010 | D19: AUT | E19: Change-password page after first sign-in | F19: New user | G19: 1. Sign in with a temporary password 2. Observe the change-password page | H19: Temporary password | I19: Change-password page shown before any other page | J19: UI | K19: Manual (exploratory) | L19: Passed | M19: Screens: ui-change-password.png (evidence/ui-screens) | N19: 2 Oct 2026 | O19: iorta QA (manual, exploratory)
A20: CS-0019 | B20: TS-02 | C20: TC-011 | D20: AUT | E20: PasswordService: generates temporary passwords that satisfy the policy | F20: Developer / CI | G20: 1. Run `npm test -w apps/api` (Vitest) 2. Locate 'PasswordService generates temporary passwords that satisfy the policy' in the run output | H20: Fixtures defined in modules/auth/password.service.spec.ts | I20: The test passes: PasswordService generates temporary passwords that satisfy the policy. | J20: Unit | K20: Automated – modules/auth/password.service.spec.ts | L20: Passed | M20: api-unit-tests.json: 'PasswordService generates temporary passwords that satisfy the policy' passed (2 Oct 2026 14:55 UTC); test-reruns.json: passed (2 Oct 2026 21:45 UTC) | N20: 2 Oct 2026 21:45 UTC | O20: iorta QA (Vitest)
A21: CS-0020 | B21: TS-03 | C21: TC-012 | D21: AUT | E21: Session cookie flags and no secrets in the sign-in response (suite) | F21: finance, support, ag-000001..3, admin | G21: 1. Run `npm run test:e2e -w apps/api` (rebuilds the iift_test database from the migrations and seeds) 2. Sign in as finance 3. Inspect Set-Cookie and body | H21: finance | I21: HttpOnly, SameSite=Strict; no passwordHash or argon2 text | J21: E2E | K21: Automated – apps/api/test/auth.e2e-spec.ts › issues an HttpOnly, SameSite=Strict session cookie and never returns secrets | L21: Passed | M21: api-e2e-tests.json: 'Authentication and session security (AP-01..04, BO-01) issues an HttpOnly, SameSite=Strict session cookie and never returns secrets' passed (2 Oct 2026 14:55 UTC); test-reruns.json: passed (2 Oct 2026 22:00 UTC) | N21: 2 Oct 2026 22:00 UTC | O21: iorta QA (Vitest e2e, iift_test database)
A22: CS-0021 | B22: TS-03 | C22: TC-012 | D22: AUT | E22: SEC-05 (OWASP A07): Session cookie is HttpOnly and SameSite=Strict (Secure is enforced in production configuration) | F22: Security tester | G22: 1. Run `node tools/security/security-checks.mjs` against a fresh non-production instance with demonstration data 2. Read the result of SEC-05 | H22: Demonstration users and records; crafted payloads as described in the script | I22: HttpOnly and SameSite=Strict; Secure enforced by production configuration | J22: Security | K22: Automated – tools/security/security-checks.mjs | L22: Passed | M22: security-checks.json: SEC-05 PASS (2 Oct 2026 14:57 UTC); evidence summarised in the Security Assessment Report | N22: 2 Oct 2026 14:57 UTC | O22: iorta QA (security-checks.mjs)
A23: CS-0022 | B23: TS-03 | C23: TC-013 | D23: AUT | E23: SEC-06 (OWASP A07): Session identifier changes at every sign-in (no session fixation) | F23: Security tester | G23: 1. Run `node tools/security/security-checks.mjs` against a fresh non-production instance with demonstration data 2. Read the result of SEC-06 | H23: Demonstration users and records; crafted payloads as described in the script | I23: New session identifier after sign-in | J23: Security | K23: Automated – tools/security/security-checks.mjs | L23: Passed | M23: security-checks.json: SEC-06 PASS (2 Oct 2026 14:57 UTC); evidence summarised in the Security Assessment Report | N23: 2 Oct 2026 14:57 UTC | O23: iorta QA (security-checks.mjs)
A24: CS-0023 | B24: TS-03 | C24: TC-014 | D24: AUT | E24: Logout ends the session server-side | F24: ag-000003 | G24: 1. Sign in as ag-000003 2. GET /api/v1/auth/me 3. POST /api/v1/auth/logout 4. GET /api/v1/auth/me with the same cookie | H24: ag-000003 | I24: GET /auth/me 200 before logout, 401 NOT_AUTHENTICATED after | J24: API | K24: Executed – API run (tools/testing/api-test-run.mjs) | L24: Passed | M24: api-test-run.json EX-007: GET /api/v1/auth/me; POST /api/v1/auth/logout; GET /api/v1/auth/me → 200 | 204 | 401 NOT_AUTHENTICATED – Please sign in | N24: 2 Oct 2026 22:12 UTC | O24: iorta TechNXT QA (API run)
A25: CS-0024 | B25: TS-03 | C25: TC-014 | D25: AUT | E25: Logout ends the session (suite) | F25: finance, support, ag-000001..3, admin | G25: 1. Run `npm run test:e2e -w apps/api` (rebuilds the iift_test database from the migrations and seeds) 2. GET /auth/me, logout, GET /auth/me | H25: ag-000002 | I25: 200; 204; 401 | J25: E2E | K25: Automated – apps/api/test/auth.e2e-spec.ts › ends the session on logout | L25: Passed | M25: api-e2e-tests.json: 'Authentication and session security (AP-01..04, BO-01) ends the session on logout' passed (2 Oct 2026 14:55 UTC); test-reruns.json: passed (2 Oct 2026 22:00 UTC) | N25: 2 Oct 2026 22:00 UTC | O25: iorta QA (Vitest e2e, iift_test database)
A26: CS-0025 | B26: TS-03 | C26: TC-014 | D26: AUT | E26: SEC-07 (OWASP A07): A session cookie cannot be reused after logout (server-side revocation) | F26: Security tester | G26: 1. Run `node tools/security/security-checks.mjs` against a fresh non-production instance with demonstration data 2. Read the result of SEC-07 | H26: Demonstration users and records; crafted payloads as described in the script | I26: Old cookie rejected (401) after logout | J26: Security | K26: Automated – tools/security/security-checks.mjs | L26: Passed | M26: security-checks.json: SEC-07 PASS (2 Oct 2026 14:57 UTC); evidence summarised in the Security Assessment Report | N26: 2 Oct 2026 14:57 UTC | O26: iorta QA (security-checks.mjs)
A27: CS-0026 | B27: TS-03 | C27: TC-015 | D27: AUT | E27: Signing in again ends the earlier session (single active session) | F27: ag-000003 | G27: 1. Sign in twice as ag-000003 2. GET /api/v1/auth/me with the first cookie | H27: security.session.single_active = true | I27: The first session receives 401 NOT_AUTHENTICATED after the second sign-in | J27: API | K27: Executed – API run (tools/testing/api-test-run.mjs) | L27: Passed | M27: api-test-run.json EX-008: Two sign-ins as ag-000003, then GET /api/v1/auth/me with the first cookie → 401 NOT_AUTHENTICATED – Please sign in | N27: 2 Oct 2026 22:12 UTC | O27: iorta TechNXT QA (API run)
A28: CS-0027 | B28: TS-03 | C28: TC-015 | D28: AUT | E28: State-changing request without the CSRF token is refused | F28: ag-000001 | G28: 1. POST /api/v1/common/notifications/read-all without x-csrf-token 2. Repeat with a forged token 3. Repeat with the session's token | H28: Session of ag-000001 | I28: HTTP 403 CSRF_TOKEN_INVALID without token and with a forged token; 204 with the session token | J28: API | K28: Executed – API run (tools/testing/api-test-run.mjs) | L28: Passed | M28: api-test-run.json EX-003: POST /api/v1/common/notifications/read-all (no token; forged token; session token) → 403 CSRF_TOKEN_INVALID – Security token missing or invalid. Refresh the page. | 403 CSRF_TOKEN_INVALID – Security token missing or invalid. Refresh the page. | 204 | N28: 2 Oct 2026 22:12 UTC | O28: iorta TechNXT QA (API run)
... A31: CS-0030 | B31: TS-03 | C31: TC-015 | D31: AUT | E31: SEC-15 (OWASP A01): State-changing requests require the session’s own CSRF token | F31: Security tester | G31: 1. Run `node tools/security/security-checks.mjs` against a fresh non-production instance with demonstration data 2. Read the result of SEC-15 | H31: Demonstration users and records; crafted payloads as described in the script | I31: 403 without the session's own CSRF token | J31: Security | K31: Automated – tools/security/security-checks.mjs | L31: Passed | M31: security-checks.json: SEC-15 PASS (2 Oct 2026 14:57 UTC); evidence summarised in the Security Assessment Report | N31: 2 Oct 2026 14:57 UTC | O31: iorta QA (security-checks.mjs)
A32: CS-0031 | B32: TS-03 | C32: TC-016 | D32: AUT | E32: Idle timeout ends the session after 15 minutes | F32: Any user | G32: 1. Sign in 2. Leave the browser idle for 16 minutes 3. Click any navigation | H32: security.session.idle_minutes = 15 | I32: Redirected to sign-in with 'session ended'; API answers 401 | J32: UI | K32: Not automated | L32: Not executed | M32: Not executed – time-based; scheduled for SIT regression (Playwright) in week 16
A33: CS-0032 | B33: TS-03 | C33: TC-016 | D33: AUT | E33: Absolute timeout ends the session after 8 hours | F33: Any user | G33: 1. Keep a session active with periodic requests for 8 h | H33: security.session.absolute_hours = 8 | I33: Session ends at 8 h regardless of activity | J33: SIT | K33: Not automated | L33: Not executed | M33: Not executed – time-based; SIT soak run
A34: CS-0033 | B34: TS-04 | C34: TC-017 | D34: AUT | E34: Lockout after five failed attempts (suite) | F34: finance, support, ag-000001..3, admin | G34: 1. Run `npm run test:e2e -w apps/api` (rebuilds the iift_test database from the migrations and seeds) 2. 5 wrong passwords for support 3. Correct password | H34: support | I34: Sixth attempt 401 ACCOUNT_LOCKED | J34: E2E | K34: Automated – apps/api/test/auth.e2e-spec.ts › locks the account after the configured number of failed attempts | L34: Passed | M34: api-e2e-tests.json: 'Authentication and session security (AP-01..04, BO-01) locks the account after the configured number of failed attempts' passed (2 Oct 2026 14:55 UTC); test-reruns.json: passed (2 Oct 2026 22:00 UTC) | N34: 2 Oct 2026 22:00 UTC | O34: iorta QA (Vitest e2e, iift_test database)
A35: CS-0034 | B35: TS-04 | C35: TC-018 | D35: AUT | E35: Account lockout after the configured failed attempts; administrator unlock | F35: qa user, manager | G35: 1. Wait 61 s for the sign-in rate limit 2. POST /api/v1/auth/login 5× with a wrong password for the user of EX-110 3. POST with the temporary password 4. As manager POST users/{id}/unlock 5. Sign in; GET /api/v1/backoffice/users 6. Disable the test user | H35: security.lockout.max_attempts = 5 | I35: 5 wrong passwords → 401; the correct password then → 401 ACCOUNT_LOCKED; unlock → 200; sign-in → 200 and back-office access refused with 403 PASSWORD_CHANGE_REQUIRED until the temporary password is changed | J35: API | K35: Executed – API run (tools/testing/api-test-run.mjs) | L35: Passed | M35: api-test-run.json EX-133: POST /api/v1/auth/login ×6; POST /api/v1/backoffice/users/{id}/unlock; sign-in; GET /api/v1/backoffice/users; disable the test user → 401,401,401,401,401 | 401 ACCOUNT_LOCKED – Your account is temporarily locked after repeated failed sign-in attempts. Try again later or contact the administrator. | unlock 200 | sign-in 200 mustChangePassword=true | 403 PASSWORD_CHANGE_REQUIRED – You must change your password before continuing | disabled 200 | N35: 2 Oct 2026 22:14 UTC | O35: iorta TechNXT QA (API run)
A36: CS-0035 | B36: TS-05 | C36: TC-019 | D36: AUT | E36: LDAP filter escaping | F36: Anonymous | G36: 1. Sign in with user name 'admin)(objectClass=*' | H36: LDAP characters | I36: 401; directory query not altered | J36: Security | K36: Not automated | L36: Not executed | M36: Not executed in this run; covered by automated check SEC-19
A37: CS-0036 | B37: TS-05 | C37: TC-019 | D37: AUT | E37: SEC-19 (OWASP A03): LDAP filter characters in usernames do not alter directory queries | F37: Security tester | G37: 1. Run `node tools/security/security-checks.mjs` against a fresh non-production instance with demonstration data 2. Read the result of SEC-19 | H37: Demonstration users and records; crafted payloads as described in the script | I37: 401; LDAP filter characters escaped | J37: Security | K37: Automated – tools/security/security-checks.mjs | L37: Passed | M37: security-checks.json: SEC-19 PASS (2 Oct 2026 14:57 UTC); evidence summarised in the Security Assessment Report | N37: 2 Oct 2026 14:57 UTC | O37: iorta QA (security-checks.mjs)
A38: CS-0037 | B38: TS-05 | C38: TC-020 | D38: AUT | E38: Back-office sign-on through IIFT Active Directory | F38: IIFT staff | G38: 1. Configure LDAP_URL and bind account 2. Sign in with a directory user 3. Attempt a reset | H38: IITH AD test OU | I38: Directory user signs in; reset refused with DIRECTORY_ACCOUNT | J38: SIT | K38: Not automated | L38: Not executed | M38: Not executed – requires IIFT environment (LDAP endpoint)
A39: CS-0038 | B39: TS-06 | C39: TC-021 | D39: ACC | E39: Unauthenticated request refused (suite) | F39: ag-000001..3, finance, ops.maker, manager, system | G39: 1. Run `npm run test:e2e -w apps/api` (rebuilds the iift_test database from the migrations and seeds) 2. GET /portal/policies without a session | H39: None | I39: 401 NOT_AUTHENTICATED | J39: E2E | K39: Automated – apps/api/test/access-control.e2e-spec.ts › rejects unauthenticated requests | L39: Passed | M39: api-e2e-tests.json: 'Access control and input handling (AP-59, BO-02, COM-02, NFR-10/14/15) rejects unauthenticated requests' passed (2 Oct 2026 14:55 UTC); test-reruns.json: passed (2 Oct 2026 22:00 UTC) | N39: 2 Oct 2026 22:00 UTC | O39: iorta QA (Vitest e2e, iift_test database)
A40: CS-0039 | B40: TS-06 | C40: TC-021 | D40: ACC | E40: SEC-09 (OWASP A01): Protected endpoints require a session | F40: Security tester | G40: 1. Run `node tools/security/security-checks.mjs` against a fresh non-production instance with demonstration data 2. Read the result of SEC-09 | H40: Demonstration users and records; crafted payloads as described in the script | I40: 401 without a session | J40: Security | K40: Automated – tools/security/security-checks.mjs | L40: Passed | M40: security-checks.json: SEC-09 PASS (2 Oct 2026 14:57 UTC); evidence summarised in the Security Assessment Report | N40: 2 Oct 2026 14:57 UTC | O40: iorta QA (security-checks.mjs)
A41: CS-0040 | B41: TS-06 | C41: TC-022 | D41: ACC | E41: Portal user cannot call back-office routes and vice versa | F41: ag-000001, finance | G41: 1. As ag-000001 GET /api/v1/backoffice/agents 2. As finance GET /api/v1/portal/policies | H41: Portal and back-office sessions | I41: HTTP 403 WRONG_AUDIENCE in both directions | J41: API | K41: Executed – API run (tools/testing/api-test-run.mjs) | L41: Passed | M41: api-test-run.json EX-004: GET /api/v1/backoffice/agents as agent; GET /api/v1/portal/policies as finance → 403 WRONG_AUDIENCE – This function is not available to your account type | 403 WRONG_AUDIENCE – This function is not available to your account type | N41: 2 Oct 2026 22:12 UTC | O41: iorta TechNXT QA (API run)
A42: CS-0041 | B42: TS-06 | C42: TC-022 | D42: ACC | E42: Audience separation (suite) | F42: ag-000001..3, finance, ops.maker, manager, system | G42: 1. Run `npm run test:e2e -w apps/api` (rebuilds the iift_test database from the migrations and seeds) 2. Agent calls back-office; finance calls portal | H42: ag-000001, finance | I42: 403 WRONG_AUDIENCE both ways | J42: E2E | K42: Automated – apps/api/test/access-control.e2e-spec.ts › keeps portal users out of the back-office API and vice versa | L42: Passed | M42: api-e2e-tests.json: 'Access control and input handling (AP-59, BO-02, COM-02, NFR-10/14/15) keeps portal users out of the back-office API and vice versa' passed (2 Oct 2026 14:55 UTC); test-reruns.json: passed (2 Oct 2026 22:00 UTC) | N42: 2 Oct 2026 22:00 UTC | O42: iorta QA (Vitest e2e, iift_test database)
A43: CS-0042 | B43: TS-06 | C43: TC-022 | D43: ACC | E43: SEC-10 (OWASP A01): Portal users cannot call back-office APIs | F43: Security tester | G43: 1. Run `node tools/security/security-checks.mjs` against a fresh non-production instance with demonstration data 2. Read the result of SEC-10 | H43: Demonstration users and records; crafted payloads as described in the script | I43: 403 WRONG_AUDIENCE for portal users on back-office routes | J43: Security | K43: Automated – tools/security/security-checks.mjs | L43: Passed | M43: security-checks.json: SEC-10 PASS (2 Oct 2026 14:57 UTC); evidence summarised in the Security Assessment Report | N43: 2 Oct 2026 14:57 UTC | O43: iorta QA (security-checks.mjs)
A44: CS-0043 | B44: TS-06 | C44: TC-023 | D44: ACC | E44: Permission guard inside the back-office | F44: ops.maker | G44: 1. As ops.maker GET /api/v1/backoffice/users | H44: ops.maker lacks bo.users.manage | I44: HTTP 403 FORBIDDEN on user administration for the operations officer | J44: API | K44: Executed – API run (tools/testing/api-test-run.mjs) | L44: Passed | M44: api-test-run.json EX-005: GET /api/v1/backoffice/users → 403 FORBIDDEN – You do not have permission to perform this action | N44: 2 Oct 2026 22:12 UTC | O44: iorta TechNXT QA (API run)
A45: CS-0044 | B45: TS-06 | C45: TC-023 | D45: ACC | E45: Permission enforced inside the back-office (suite) | F45: ag-000001..3, finance, ops.maker, manager, system | G45: 1. Run `npm run test:e2e -w apps/api` (rebuilds the iift_test database from the migrations and seeds) 2. ops.maker GET /backoffice/users | H45: ops.maker | I45: 403 FORBIDDEN | J45: E2E | K45: Automated – apps/api/test/access-control.e2e-spec.ts › enforces permissions within the back-office | L45: Passed | M45: api-e2e-tests.json: 'Access control and input handling (AP-59, BO-02, COM-02, NFR-10/14/15) enforces permissions within the back-office' passed (2 Oct 2026 14:55 UTC); test-reruns.json: passed (2 Oct 2026 22:00 UTC) | N45: 2 Oct 2026 22:00 UTC | O45: iorta QA (Vitest e2e, iift_test database)
A46: CS-0045 | B46: TS-06 | C46: TC-024 | D46: ACC | E46: SEC-14 (OWASP A01): Users cannot grant themselves permissions they do not hold | F46: Security tester | G46: 1. Run `node tools/security/security-checks.mjs` against a fresh non-production instance with demonstration data 2. Read the result of SEC-14 | H46: Demonstration users and records; crafted payloads as described in the script | I46: 403 when granting permissions the user does not hold | J46: Security | K46: Automated – tools/security/security-checks.mjs | L46: Passed | M46: security-checks.json: SEC-14 PASS (2 Oct 2026 14:57 UTC); evidence summarised in the Security Assessment Report | N46: 2 Oct 2026 14:57 UTC | O46: iorta QA (security-checks.mjs)
A47: CS-0046 | B47: TS-06 | C47: TC-025 | D47: ACC | E47: Not-authorised page for a missing permission | F47: support | G47: 1. Open a back-office page the role lacks | H47: support desk role | I47: Not-authorised page shown; menu entry absent | J47: UI | K47: Manual (exploratory) | L47: Passed | M47: Screens: b-final-roles.png (evidence/ui-screens) | N47: 2 Oct 2026 | O47: iorta QA (manual, exploratory)
A48: CS-0047 | B48: TS-07 | C48: TC-026 | D48: ACC | E48: Hierarchy and agency scoping of policies (suite) | F48: ag-000001..3, finance, ops.maker, manager, system | G48: 1. Run `npm run test:e2e -w apps/api` (rebuilds the iift_test database from the migrations and seeds) 2. Policy of AG-000001 read by ag-000003, ag-000002 and ag-000001 | H48: Main agent policy | I48: 404; 404; 200 | J48: E2E | K48: Automated – apps/api/test/access-control.e2e-spec.ts › restricts records to the agent hierarchy and agency | L48: Passed | M48: api-e2e-tests.json: 'Access control and input handling (AP-59, BO-02, COM-02, NFR-10/14/15) restricts records to the agent hierarchy and agency' passed (2 Oct 2026 14:55 UTC); test-reruns.json: passed (2 Oct 2026 22:00 UTC) | N48: 2 Oct 2026 22:00 UTC | O48: iorta QA (Vitest e2e, iift_test database)
A49: CS-0048 | B49: TS-07 | C49: TC-026 | D49: ACC | E49: SEC-11 (OWASP A01): Another agency's policy cannot be read by changing the identifier (IDOR) | F49: Security tester | G49: 1. Run `node tools/security/security-checks.mjs` against a fresh non-production instance with demonstration data 2. Read the result of SEC-11 | H49: Demonstration users and records; crafted payloads as described in the script | I49: 404: record outside the user's agency is not disclosed | J49: Security | K49: Automated – tools/security/security-checks.mjs | L49: Passed | M49: security-checks.json: SEC-11 PASS (2 Oct 2026 14:57 UTC); evidence summarised in the Security Assessment Report | N49: 2 Oct 2026 14:57 UTC | O49: iorta QA (security-checks.mjs)
A50: CS-0049 | B50: TS-07 | C50: TC-027 | D50: ACC | E50: Sub-agents see their own business; the principal sees the whole agency | F50: ag-000001, ag-000002 | G50: 1. As ag-000002 GET /api/v1/portal/policies 2. As ag-000001 GET /api/v1/portal/policies 3. Compare agent codes and totals | H50: Agency AGY-SA: principal AG-000001, sub-agent AG-000002 | I50: ag-000002 lists only policies with agent AG-000002; ag-000001 lists more policies, including those of AG-000002 | J50: API | K50: Executed – API run (tools/testing/api-test-run.mjs) | L50: Passed | M50: api-test-run.json EX-009: GET /api/v1/portal/policies as ag-000002 and as ag-000001 → sub-agent total=13 onlyOwn=true | principal total=46 includesSubAgent=true | N50: 2 Oct 2026 22:13 UTC | O50: iorta TechNXT QA (API run)
... A65: CS-0064 | B65: TS-09 | C65: TC-036 | D65: AGT | E65: Maker withdraws a pending request | F65: ag-000001 | G65: 1. Open My requests 2. Withdraw the agent registration | H65: Pending request | I65: Status WITHDRAWN; agent no longer pending | J65: UI | K65: Manual (exploratory) | L65: Passed | M65: Screens: b-flow-maker-view.png, b-flow-agent-after-withdraw.png (evidence/ui-screens) | N65: 2 Oct 2026 | O65: iorta QA (manual, exploratory)
A66: CS-0065 | B66: TS-10 | C66: TC-037 | D66: AGT | E66: Agent search filters | F66: ops.maker | G66: 1. Filter agents by agency, status and type | H66: Seeded agents | I66: Matching records only | J66: UI | K66: Not automated | L66: Not executed | M66: Not executed – UI under restyling
A67: CS-0066 | B67: TS-10 | C67: TC-038 | D67: AGT | E67: Agent status change request with an invalid transition is refused | F67: ops.maker | G67: 1. As ops.maker POST /api/v1/backoffice/agents/{AG-000003}/status-requests ACTIVE 2. POST SUSPENDED with a reason 3. POST approvals/{id}/withdraw | H67: Active main agent AG-000003 | I67: ACTIVE → ACTIVE refused with 422 INVALID_STATUS_CHANGE; ACTIVE → SUSPENDED creates a request (201) | J67: API | K67: Executed – API run (tools/testing/api-test-run.mjs) | L67: Passed | M67: api-test-run.json EX-078: POST /api/v1/backoffice/agents/f8fad9ca-f327-4a4a-b2aa-c516fb82000f/status-requests (ACTIVE; SUSPENDED); withdraw → 422 INVALID_STATUS_CHANGE – Status cannot change from ACTIVE to ACTIVE | 201 PENDING | withdraw 200 WITHDRAWN | N67: 2 Oct 2026 22:13 UTC | O67: iorta TechNXT QA (API run)
A68: CS-0067 | B68: TS-10 | C68: TC-038 | D68: AGT | E68: Agent status change request and approval detail | F68: ops.maker, ops.checker | G68: 1. Open an agent 2. Request a status change 3. Checker opens the approval | H68: Suspend AG-000003 | I68: Status modal validates reason; approval shows the change | J68: UI | K68: Manual (exploratory) | L68: Passed | M68: Screens: b-flow-status-modal.png, b-bo-approval-agent.png (evidence/ui-screens) | N68: 2 Oct 2026 | O68: iorta QA (manual, exploratory)
A69: CS-0068 | B69: TS-10 | C69: TC-039 | D69: AGT | E69: Agency maintenance: validation and creation | F69: manager | G69: 1. As manager POST /api/v1/backoffice/agencies with code 'bad code' 2. POST with code AGY-<run>, channel AGENCY | H69: New agency | I69: Invalid code → 400; valid agency → 201 with status ACTIVE | J69: API | K69: Executed – API run (tools/testing/api-test-run.mjs) | L69: Passed | M69: api-test-run.json EX-079: POST /api/v1/backoffice/agencies → 400 | 201 AGY-RIR5X2 ACTIVE | N69: 2 Oct 2026 22:13 UTC | O69: iorta TechNXT QA (API run)
A70: CS-0069 | B70: TS-10 | C70: TC-039 | D70: AGT | E70: Agency maintenance | F70: manager | G70: 1. Agencies & banks → New 2. Submit invalid, then valid data 3. Open the agency | H70: New agency | I70: Validation shown; agency created and listed with its agents | J70: UI | K70: Manual (exploratory) | L70: Passed | M70: Screens: b-bo-agencies.png, b-flow-agency-validation.png, b-flow-agency-detail.png (evidence/ui-screens) | N70: 2 Oct 2026 | O70: iorta QA (manual, exploratory)
A71: CS-0070 | B71: TS-10 | C71: TC-040 | D71: AGT | E71: Back-office agent registration with validation | F71: ops.maker | G71: 1. Agents & bankers → New agent 2. Submit with invalid data 3. Submit valid data | H71: Agent under AGY-DT | I71: Validation messages; agent registered pending approval | J71: UI | K71: Manual (exploratory) | L71: Passed | M71: Screens: b-bo-agent-new.png, b-flow-bo-register-filled.png, b-flow-bo-registered.png (evidence/ui-screens) | N71: 2 Oct 2026 | O71: iorta QA (manual, exploratory)
A72: CS-0071 | B72: TS-11 | C72: TC-041 | D72: PAR | E72: Corporate participant must use a business registration number | F72: ag-000001 | G72: 1. POST /api/v1/portal/participants type CORPORATE with idType NRIC | H72: Syarikat Contoh Sdn Bhd | I72: HTTP 422 INVALID_ID_TYPE | J72: API | K72: Executed – API run (tools/testing/api-test-run.mjs) | L72: Passed | M72: api-test-run.json EX-012: POST /api/v1/portal/participants (CORPORATE with NRIC) → 422 INVALID_ID_TYPE – Corporate participants are identified by business registration number | N72: 2 Oct 2026 22:13 UTC | O72: iorta TechNXT QA (API run)
A73: CS-0072 | B73: TS-11 | C73: TC-042 | D73: PAR | E73: Register an individual participant | F73: ag-000001 | G73: 1. POST /api/v1/portal/participants with an individual NRIC participant 2. Inspect participantNo, amlStatus and idNumberMasked | H73: Nur Hidayah binti Kamal, NRIC 01-9nnnnn, class 1 professional | I73: HTTP 201; participantNo PT/yy/nnnnnn; amlStatus CLEAR; IC returned masked only | J73: API | K73: Executed – API run (tools/testing/api-test-run.mjs) | L73: Passed | M73: api-test-run.json EX-010: POST /api/v1/portal/participants (NRIC, class 1 professional) → 201 PT/26/000076 aml=CLEAR id=*****8603 | N73: 2 Oct 2026 22:13 UTC | O73: iorta TechNXT QA (API run)
A74: CS-0073 | B74: TS-11 | C74: TC-042 | D74: PAR | E74: Journey: participant registered and auto-cleared by AML (suite) | F74: ag-000002, bk-000004, ops.maker, finance, underwriter | G74: 1. Run `npm run test:e2e -w apps/api` (rebuilds the iift_test database from the migrations and seeds) 2. POST /portal/participants Nur Hidayah binti Kamal | H74: NRIC 01-990011 | I74: 201; amlStatus CLEAR | J74: E2E | K74: Automated – apps/api/test/policy-lifecycle.e2e-spec.ts › runs the full Professional Takaful Plan journey with maker-checker payment verification | L74: Passed | M74: api-e2e-tests.json: 'Quotation to e-Policy and e-Receipt (FFR03, AP-17..45, BO-16..19) runs the full Professional Takaful Plan journey with maker-checker payment verification' passed (2 Oct 2026 14:55 UTC); test-reruns.json: passed (2 Oct 2026 22:00 UTC) | N74: 2 Oct 2026 22:00 UTC | O74: iorta QA (Vitest e2e, iift_test database)
A75: CS-0074 | B75: TS-11 | C75: TC-042 | D75: PAR | E75: Participant registration and update request | F75: ag-000001 | G75: 1. Open Participants 2. New participant 3. Save 4. Edit and submit an update | H75: Individual participant | I75: Participant created with number; update request pending approval | J75: UI | K75: Manual (exploratory) | L75: Passed | M75: Screens: a-participants.png, a-participant-new.png, a-participant-created.png, a-participant-update.png (evidence/ui-screens) | N75: 2 Oct 2026 | O75: iorta QA (manual, exploratory)
A76: CS-0075 | B76: TS-11 | C76: TC-043 | D76: PAR | E76: Participant search in the back-office | F76: ops.maker | G76: 1. Search by name, number and exact ID | H76: Seeded participants | I76: Matching records only | J76: UI | K76: Not automated | L76: Not executed | M76: Not executed – UI under restyling; API list verified in the suites
A77: CS-0076 | B77: TS-11 | C77: TC-044 | D77: PAR | E77: Participant update goes through approval; empty and duplicate requests are refused | F77: ag-000001 | G77: 1. POST /api/v1/portal/participants/{id}/update-requests with an empty body 2. POST with mobile and addressLine2 changed 3. POST another change while the first is pending | H77: Participant of EX-010 | I77: Empty body → 422 NO_CHANGES; a change → 201 approval request (PARTICIPANT_UPDATE, PENDING) with before/after values; a second request while one is pending → 422 REQUEST_ALREADY_PENDING | J77: API | K77: Executed – API run (tools/testing/api-test-run.mjs) | L77: Passed | M77: api-test-run.json EX-016: POST /api/v1/portal/participants/6558a123-ebc2-4cd2-878e-79354f702c6b/update-requests (empty; changed mobile; another change) → 422 NO_CHANGES – No changes were submitted | 201 PARTICIPANT_UPDATE PENDING before={"mobile":"6738111222","addressLine2":null} | 422 REQUEST_ALREADY_PENDING – A request for this record is already awaiting approval | N77: 2 Oct 2026 22:13 UTC | O77: iorta TechNXT QA (API run)
A78: CS-0077 | B78: TS-12 | C78: TC-045 | D78: PAR | E78: Duplicate participant (same IC) is refused with the existing record | F78: ag-000001 | G78: 1. POST /api/v1/portal/participants again with the same NRIC | H78: Same IC as EX-010 | I78: HTTP 422 DUPLICATE_PARTICIPANT naming the existing participant number | J78: API | K78: Executed – API run (tools/testing/api-test-run.mjs) | L78: Passed | M78: api-test-run.json EX-011: POST /api/v1/portal/participants (same IC) → 422 DUPLICATE_PARTICIPANT – This participant is already registered as PT/26/000076 [6558a123-ebc2-4cd2-878e-79354f702c6b] | N78: 2 Oct 2026 22:13 UTC | O78: iorta TechNXT QA (API run)
A79: CS-0078 | B79: TS-12 | C79: TC-045 | D79: PAR | E79: Duplicate participant detected in the wizard | F79: ag-000001 | G79: 1. In the participant step enter an IC already registered 2. Click Register | H79: Existing IC | I79: Warning names the existing participant number and offers 'Use existing participant' | J79: UI | K79: Manual (exploratory) | L79: Passed | M79: Screens: a-wizard-duplicate.png, a-wizard-duplicate-used.png, a-participant-duplicate.png (evidence/ui-screens) | N79: 2 Oct 2026 | O79: iorta QA (manual, exploratory)
A80: CS-0079 | B80: TS-12 | C80: TC-046 | D80: PAR | E80: Exact-ID lookup from another agency returns a masked summary only (single shared profile) | F80: ag-000003 | G80: 1. As ag-000003 GET /api/v1/portal/participants/lookup?idType=NRIC&idNumber=<EX-010 IC> | H80: Participant of agency AGY-SA | I80: HTTP 200 found=true with participant number and masked name; no address or contact details | J80: API | K80: Executed – API run (tools/testing/api-test-run.mjs) | L80: Passed | M80: api-test-run.json EX-014: GET /api/v1/portal/participants/lookup → 200 {"found":true,"participant":{"id":"6558a123-ebc2-4cd2-878e-79354f702c6b","participantNo":"PT/26/000076","fullName":"Nur Hidayah binti Kamal RIR5X2","idNumberMas | N80: 2 Oct 2026 22:13 UTC | O80: iorta TechNXT QA (API run)
A81: CS-0080 | B81: TS-12 | C81: TC-047 | D81: PAR | E81: Full profile is not visible to an agency without business with the participant | F81: ag-000003 | G81: 1. As ag-000003 GET /api/v1/portal/participants/{id of EX-010} | H81: No business between AGY-DT and the participant | I81: HTTP 403 or 404 (not disclosed) | J81: API | K81: Executed – API run (tools/testing/api-test-run.mjs) | L81: Passed | M81: api-test-run.json EX-015: GET /api/v1/portal/participants/6558a123-ebc2-4cd2-878e-79354f702c6b → 403 FORBIDDEN – This participant is not shared with your agency | N81: 2 Oct 2026 22:13 UTC | O81: iorta TechNXT QA (API run)
A82: CS-0081 | B82: TS-12 | C82: TC-047 | D82: PAR | E82: SEC-13 (OWASP A01): Participant profiles are limited to agencies that hold business with them | F82: Security tester | G82: 1. Run `node tools/security/security-checks.mjs` against a fresh non-production instance with demonstration data 2. Read the result of SEC-13 | H82: Demonstration users and records; crafted payloads as described in the script | I82: 403 for participants with no business in the user's agency | J82: Security | K82: Automated – tools/security/security-checks.mjs | L82: Passed | M82: security-checks.json: SEC-13 PASS (2 Oct 2026 14:57 UTC); evidence summarised in the Security Assessment Report | N82: 2 Oct 2026 14:57 UTC | O82: iorta QA (security-checks.mjs)
A83: CS-0082 | B83: TS-13 | C83: TC-048 | D83: AML | E83: name matching: implements Jaro-Winkler | F83: Developer / CI | G83: 1. Run `npm test -w apps/api` (Vitest) 2. Locate 'name matching implements Jaro-Winkler' in the run output | H83: Fixtures defined in modules/aml/name-matching.spec.ts | I83: The test passes: name matching implements Jaro-Winkler. | J83: Unit | K83: Automated – modules/aml/name-matching.spec.ts | L83: Passed | M83: api-unit-tests.json: 'name matching implements Jaro-Winkler' passed (2 Oct 2026 14:55 UTC); test-reruns.json: passed (2 Oct 2026 21:45 UTC) | N83: 2 Oct 2026 21:45 UTC | O83: iorta QA (Vitest)
A84: CS-0083 | B84: TS-13 | C84: TC-048 | D84: AML | E84: name matching: normalises case, punctuation, honorifics and common spellings | F84: Developer / CI | G84: 1. Run `npm test -w apps/api` (Vitest) 2. Locate 'name matching normalises case, punctuation, honorifics and common spellings' in the run output | H84: Fixtures defined in modules/aml/name-matching.spec.ts | I84: The test passes: name matching normalises case, punctuation, honorifics and common spellings. | J84: Unit | K84: Automated – modules/aml/name-matching.spec.ts | L84: Passed | M84: api-unit-tests.json: 'name matching normalises case, punctuation, honorifics and common spellings' passed (2 Oct 2026 14:55 UTC); test-reruns.json: passed (2 Oct 2026 21:45 UTC) | N84: 2 Oct 2026 21:45 UTC | O84: iorta QA (Vitest)
A85: CS-0084 | B85: TS-13 | C85: TC-048 | D85: AML | E85: name matching: scores close transliterations above the default review threshold | F85: Developer / CI | G85: 1. Run `npm test -w apps/api` (Vitest) 2. Locate 'name matching scores close transliterations above the default review threshold' in the run output | H85: Fixtures defined in modules/aml/name-matching.spec.ts | I85: The test passes: name matching scores close transliterations above the default review threshold. | J85: Unit | K85: Automated – modules/aml/name-matching.spec.ts | L85: Passed | M85: api-unit-tests.json: 'name matching scores close transliterations above the default review threshold' passed (2 Oct 2026 14:55 UTC); test-reruns.json: passed (2 Oct 2026 21:45 UTC) | N85: 2 Oct 2026 21:45 UTC | O85: iorta QA (Vitest)
A86: CS-0085 | B86: TS-13 | C86: TC-048 | D86: AML | E86: name matching: scores identical names 100 regardless of honorific | F86: Developer / CI | G86: 1. Run `npm test -w apps/api` (Vitest) 2. Locate 'name matching scores identical names 100 regardless of honorific' in the run output | H86: Fixtures defined in modules/aml/name-matching.spec.ts | I86: The test passes: name matching scores identical names 100 regardless of honorific. | J86: Unit | K86: Automated – modules/aml/name-matching.spec.ts | L86: Passed | M86: api-unit-tests.json: 'name matching scores identical names 100 regardless of honorific' passed (2 Oct 2026 14:55 UTC); test-reruns.json: passed (2 Oct 2026 21:45 UTC) | N86: 2 Oct 2026 21:45 UTC | O86: iorta QA (Vitest)
A87: CS-0086 | B87: TS-13 | C87: TC-048 | D87: AML | E87: name matching: scores unrelated names low | F87: Developer / CI | G87: 1. Run `npm test -w apps/api` (Vitest) 2. Locate 'name matching scores unrelated names low' in the run output | H87: Fixtures defined in modules/aml/name-matching.spec.ts | I87: The test passes: name matching scores unrelated names low. | J87: Unit | K87: Automated – modules/aml/name-matching.spec.ts | L87: Passed | M87: api-unit-tests.json: 'name matching scores unrelated names low' passed (2 Oct 2026 14:55 UTC); test-reruns.json: passed (2 Oct 2026 21:45 UTC) | N87: 2 Oct 2026 21:45 UTC | O87: iorta QA (Vitest)
A88: CS-0087 | B88: TS-13 | C88: TC-048 | D88: AML | E88: Participant matching a watch-list name is flagged and routed to Compliance | F88: ag-000001 | G88: 1. POST /api/v1/portal/participants 'Rashid Al Mansouri' (passport) 2. Create a KHR quotation; complete questionnaire, nominee, documents, signature 3. POST /submit | H88: Watch-list DEMO-PEP entry; aml.match_threshold = 85 | I88: HTTP 201 with amlStatus FLAGGED; quotation submission → 422 AML_REVIEW_PENDING | J88: API | K88: Executed – API run (tools/testing/api-test-run.mjs) | L88: Passed | M88: api-test-run.json EX-080: POST /api/v1/portal/participants (Rashid Al Mansouri); … submit → 201 aml=FLAGGED | 422 AML_REVIEW_PENDING – The participant is under compliance review. Submission is possible once Compliance clears the case. | N88: 2 Oct 2026 22:13 UTC | O88: iorta TechNXT QA (API run)
... A106: CS-0105 | B106: TS-15 | C106: TC-057 | D106: PRD | E106: FinancingRatingEngine: validates its configuration | F106: Developer / CI | G106: 1. Run `npm test -w apps/api` (Vitest) 2. Locate 'FinancingRatingEngine validates its configuration' in the run output | H106: Fixtures defined in modules/products/rating/financing.engine.spec.ts | I106: The test passes: FinancingRatingEngine validates its configuration. | J106: Unit | K106: Automated – modules/products/rating/financing.engine.spec.ts | L106: Passed | M106: api-unit-tests.json: 'FinancingRatingEngine validates its configuration' passed (2 Oct 2026 14:55 UTC); test-reruns.json: passed (2 Oct 2026 21:45 UTC) | N106: 2 Oct 2026 21:45 UTC | O106: iorta QA (Vitest)
A107: CS-0106 | B107: TS-15 | C107: TC-057 | D107: PRD | E107: Property financing with profit basis NONE | F107: Agent | G107: 1. Quote PFT 200,000 over 240 months | H107: profitBasis NONE | I107: No profit loading in the sum covered | J107: API | K107: Not automated | L107: Not executed | M107: Not executed in this run; unit-tested in the financing engine
A108: CS-0107 | B108: TS-16 | C108: TC-058 | D108: PRD | E108: FixedPlanRatingEngine › Overseas Student Assist eligibility (FFR05): accepts a registered Brunei citizen student | F108: Developer / CI | G108: 1. Run `npm test -w apps/api` (Vitest) 2. Locate 'FixedPlanRatingEngine Overseas Student Assist eligibility (FFR05) accepts a registered Brunei citizen student' in the run output | H108: Fixtures defined in modules/products/rating/fixed-plan.engine.spec.ts | I108: The test passes: FixedPlanRatingEngine › Overseas Student Assist eligibility (FFR05) accepts a registered Brunei citizen student. | J108: Unit | K108: Automated – modules/products/rating/fixed-plan.engine.spec.ts | L108: Passed | M108: api-unit-tests.json: 'FixedPlanRatingEngine Overseas Student Assist eligibility (FFR05) accepts a registered Brunei citizen student' passed (2 Oct 2026 14:55 UTC); test-reruns.json: passed (2 Oct 2026 21:45 UTC) | N108: 2 Oct 2026 21:45 UTC | O108: iorta QA (Vitest)
A109: CS-0108 | B109: TS-16 | C109: TC-058 | D109: PRD | E109: FixedPlanRatingEngine › Overseas Student Assist eligibility (FFR05): rejects a participant who is not a Brunei citizen | F109: Developer / CI | G109: 1. Run `npm test -w apps/api` (Vitest) 2. Locate 'FixedPlanRatingEngine Overseas Student Assist eligibility (FFR05) rejects a participant who is not a Brunei citizen' in the run output | H109: Fixtures defined in modules/products/rating/fixed-plan.engine.spec.ts | I109: The test passes: FixedPlanRatingEngine › Overseas Student Assist eligibility (FFR05) rejects a participant who is not a Brunei citizen. | J109: Unit | K109: Automated – modules/products/rating/fixed-plan.engine.spec.ts | L109: Passed | M109: api-unit-tests.json: 'FixedPlanRatingEngine Overseas Student Assist eligibility (FFR05) rejects a participant who is not a Brunei citizen' passed (2 Oct 2026 14:55 UTC); test-reruns.json: passed (2 Oct 2026 21:45 UTC) | N109: 2 Oct 2026 21:45 UTC | O109: iorta QA (Vitest)
A110: CS-0109 | B110: TS-16 | C110: TC-058 | D110: PRD | E110: FixedPlanRatingEngine › Overseas Student Assist eligibility (FFR05): rejects participants older than 65 next birthday | F110: Developer / CI | G110: 1. Run `npm test -w apps/api` (Vitest) 2. Locate 'FixedPlanRatingEngine Overseas Student Assist eligibility (FFR05) rejects participants older than 65 next birthday' in the run output | H110: Fixtures defined in modules/products/rating/fixed-plan.engine.spec.ts | I110: The test passes: FixedPlanRatingEngine › Overseas Student Assist eligibility (FFR05) rejects participants older than 65 next birthday. | J110: Unit | K110: Automated – modules/products/rating/fixed-plan.engine.spec.ts | L110: Passed | M110: api-unit-tests.json: 'FixedPlanRatingEngine Overseas Student Assist eligibility (FFR05) rejects participants older than 65 next birthday' passed (2 Oct 2026 14:55 UTC); test-reruns.json: passed (2 Oct 2026 21:45 UTC) | N110: 2 Oct 2026 21:45 UTC | O110: iorta QA (Vitest)
A111: CS-0110 | B111: TS-16 | C111: TC-058 | D111: PRD | E111: FixedPlanRatingEngine › Overseas Student Assist eligibility (FFR05): requires confirmation of student registration | F111: Developer / CI | G111: 1. Run `npm test -w apps/api` (Vitest) 2. Locate 'FixedPlanRatingEngine Overseas Student Assist eligibility (FFR05) requires confirmation of student registration' in the run output | H111: Fixtures defined in modules/products/rating/fixed-plan.engine.spec.ts | I111: The test passes: FixedPlanRatingEngine › Overseas Student Assist eligibility (FFR05) requires confirmation of student registration. | J111: Unit | K111: Automated – modules/products/rating/fixed-plan.engine.spec.ts | L111: Passed | M111: api-unit-tests.json: 'FixedPlanRatingEngine Overseas Student Assist eligibility (FFR05) requires confirmation of student registration' passed (2 Oct 2026 14:55 UTC); test-reruns.json: passed (2 Oct 2026 21:45 UTC) | N111: 2 Oct 2026 21:45 UTC | O111: iorta QA (Vitest)
A112: CS-0111 | B112: TS-16 | C112: TC-058 | D112: PRD | E112: FixedPlanRatingEngine: prices Professional Plan B with the optional additional cover (FFR03) | F112: Developer / CI | G112: 1. Run `npm test -w apps/api` (Vitest) 2. Locate 'FixedPlanRatingEngine prices Professional Plan B with the optional additional cover (FFR03)' in the run output | H112: Fixtures defined in modules/products/rating/fixed-plan.engine.spec.ts | I112: The test passes: FixedPlanRatingEngine prices Professional Plan B with the optional additional cover (FFR03). | J112: Unit | K112: Automated – modules/products/rating/fixed-plan.engine.spec.ts | L112: Passed | M112: api-unit-tests.json: 'FixedPlanRatingEngine prices Professional Plan B with the optional additional cover (FFR03)' passed (2 Oct 2026 14:55 UTC); test-reruns.json: passed (2 Oct 2026 21:45 UTC) | N112: 2 Oct 2026 21:45 UTC | O112: iorta QA (Vitest)
A113: CS-0112 | B113: TS-16 | C113: TC-058 | D113: PRD | E113: Professional Plan B with additional cover is rated 135 + 120 | F113: ag-000001 | G113: 1. POST /api/v1/portal/policies/calculate PRO plan B additionalCover=true | H113: Participant of EX-010 (class 1) | I113: contribution 255.00, sumCovered 30,000 | J113: API | K113: Executed – API run (tools/testing/api-test-run.mjs) | L113: Passed | M113: api-test-run.json EX-021: POST /api/v1/portal/policies/calculate (PRO, plan B, additional cover) → 200 contribution=255 sumCovered=30000 | N113: 2 Oct 2026 22:13 UTC | O113: iorta TechNXT QA (API run)
A114: CS-0113 | B114: TS-16 | C114: TC-058 | D114: PRD | E114: Journey: Professional Plan A with additional cover rated 165 (suite) | F114: ag-000002, bk-000004, ops.maker, finance, underwriter | G114: 1. Run `npm run test:e2e -w apps/api` (rebuilds the iift_test database from the migrations and seeds) 2. POST /portal/policies/calculate PRO plan A additionalCover | H114: 75 + 90 | I114: contribution '165' | J114: E2E | K114: Automated – apps/api/test/policy-lifecycle.e2e-spec.ts › runs the full Professional Takaful Plan journey with maker-checker payment verification | L114: Passed | M114: api-e2e-tests.json: 'Quotation to e-Policy and e-Receipt (FFR03, AP-17..45, BO-16..19) runs the full Professional Takaful Plan journey with maker-checker payment verification' passed (2 Oct 2026 14:55 UTC); test-reruns.json: passed (2 Oct 2026 22:00 UTC) | N114: 2 Oct 2026 22:00 UTC | O114: iorta QA (Vitest e2e, iift_test database)
A115: CS-0114 | B115: TS-16 | C115: TC-059 | D115: PRD | E115: FixedPlanRatingEngine: accepts only Occupational Class I for the Professional plan | F115: Developer / CI | G115: 1. Run `npm test -w apps/api` (Vitest) 2. Locate 'FixedPlanRatingEngine accepts only Occupational Class I for the Professional plan' in the run output | H115: Fixtures defined in modules/products/rating/fixed-plan.engine.spec.ts | I115: The test passes: FixedPlanRatingEngine accepts only Occupational Class I for the Professional plan. | J115: Unit | K115: Automated – modules/products/rating/fixed-plan.engine.spec.ts | L115: Passed | M115: api-unit-tests.json: 'FixedPlanRatingEngine accepts only Occupational Class I for the Professional plan' passed (2 Oct 2026 14:55 UTC); test-reruns.json: passed (2 Oct 2026 21:45 UTC) | N115: 2 Oct 2026 21:45 UTC | O115: iorta QA (Vitest)
A116: CS-0115 | B116: TS-16 | C116: TC-059 | D116: PRD | E116: Professional Plan accepts Occupational Class I only | F116: ag-000001 | G116: 1. Register a participant with occupationClass 3 2. POST /api/v1/portal/policies/calculate PRO plan A | H116: SKILLED_MANUAL, class 3 | I116: HTTP 422 NOT_ELIGIBLE for a class 3 participant | J116: API | K116: Executed – API run (tools/testing/api-test-run.mjs) | L116: Passed | M116: api-test-run.json EX-025: POST /api/v1/portal/policies/calculate (PRO, occupation class 3) → 422 NOT_ELIGIBLE – The quotation does not meet the product rules [Only occupational class 1 is eligible] | N116: 2 Oct 2026 22:13 UTC | O116: iorta TechNXT QA (API run)
A117: CS-0116 | B117: TS-17 | C117: TC-060 | D117: PRD | E117: FixedPlanRatingEngine: applies the Wider (Child) loading for Khairat (FFR04) | F117: Developer / CI | G117: 1. Run `npm test -w apps/api` (Vitest) 2. Locate 'FixedPlanRatingEngine applies the Wider (Child) loading for Khairat (FFR04)' in the run output | H117: Fixtures defined in modules/products/rating/fixed-plan.engine.spec.ts | I117: The test passes: FixedPlanRatingEngine applies the Wider (Child) loading for Khairat (FFR04). | J117: Unit | K117: Automated – modules/products/rating/fixed-plan.engine.spec.ts | L117: Passed | M117: api-unit-tests.json: 'FixedPlanRatingEngine applies the Wider (Child) loading for Khairat (FFR04)' passed (2 Oct 2026 14:55 UTC); test-reruns.json: passed (2 Oct 2026 21:45 UTC) | N117: 2 Oct 2026 21:45 UTC | O117: iorta QA (Vitest)
A118: CS-0117 | B118: TS-17 | C118: TC-060 | D118: PRD | E118: FixedPlanRatingEngine: requires a coverage type when the product defines them | F118: Developer / CI | G118: 1. Run `npm test -w apps/api` (Vitest) 2. Locate 'FixedPlanRatingEngine requires a coverage type when the product defines them' in the run output | H118: Fixtures defined in modules/products/rating/fixed-plan.engine.spec.ts | I118: The test passes: FixedPlanRatingEngine requires a coverage type when the product defines them. | J118: Unit | K118: Automated – modules/products/rating/fixed-plan.engine.spec.ts | L118: Passed | M118: api-unit-tests.json: 'FixedPlanRatingEngine requires a coverage type when the product defines them' passed (2 Oct 2026 14:55 UTC); test-reruns.json: passed (2 Oct 2026 21:45 UTC) | N118: 2 Oct 2026 21:45 UTC | O118: iorta QA (Vitest)
A119: CS-0118 | B119: TS-17 | C119: TC-060 | D119: PRD | E119: Khairat Plan A with Wider (Child) cover applies the 1.6 loading | F119: ag-000001 | G119: 1. POST /api/v1/portal/policies/calculate KHR plan A coverageType WIDER | H119: Participant of EX-010 | I119: contribution 64.00 (40 × 1.6) | J119: API | K119: Executed – API run (tools/testing/api-test-run.mjs) | L119: Passed | M119: api-test-run.json EX-022: POST /api/v1/portal/policies/calculate (KHR, plan A, WIDER) → 200 contribution=64 | N119: 2 Oct 2026 22:13 UTC | O119: iorta TechNXT QA (API run)
A120: CS-0119 | B120: TS-17 | C120: TC-061 | D120: PRD | E120: Khairat renewal unavailable in the portal UI | F120: Agent | G120: 1. Open an active Khairat policy | H120: KHR | I120: No Renew action | J120: UI | K120: Not automated | L120: Not executed | M120: Not executed – UI under restyling; API rule verified in EX-065
A121: CS-0120 | B121: TS-18 | C121: TC-062 | D121: PRD | E121: FixedPlanRatingEngine: offers 1- and 2-year cover for Personal Home Assistant (FFR02) | F121: Developer / CI | G121: 1. Run `npm test -w apps/api` (Vitest) 2. Locate 'FixedPlanRatingEngine offers 1- and 2-year cover for Personal Home Assistant (FFR02)' in the run output | H121: Fixtures defined in modules/products/rating/fixed-plan.engine.spec.ts | I121: The test passes: FixedPlanRatingEngine offers 1- and 2-year cover for Personal Home Assistant (FFR02). | J121: Unit | K121: Automated – modules/products/rating/fixed-plan.engine.spec.ts | L121: Passed | M121: api-unit-tests.json: 'FixedPlanRatingEngine offers 1- and 2-year cover for Personal Home Assistant (FFR02)' passed (2 Oct 2026 14:55 UTC); test-reruns.json: passed (2 Oct 2026 21:45 UTC) | N121: 2 Oct 2026 21:45 UTC | O121: iorta QA (Vitest)
A122: CS-0121 | B122: TS-18 | C122: TC-062 | D122: PRD | E122: Personal Home Assistant two-year cover | F122: ag-000001 | G122: 1. POST /api/v1/portal/policies/calculate PHA plan STANDARD termMonths 24 with helper details | H122: Helper Maria Santos, passport P8827361A | I122: contribution 220.00 for 24 months | J122: API | K122: Executed – API run (tools/testing/api-test-run.mjs) | L122: Passed | M122: api-test-run.json EX-023: POST /api/v1/portal/policies/calculate (PHA, 24 months) → 200 contribution=220 | N122: 2 Oct 2026 22:13 UTC | O122: iorta TechNXT QA (API run)
A123: CS-0122 | B123: TS-19 | C123: TC-063 | D123: PRD | E123: Overseas Student Tertiary plan | F123: Agent | G123: 1. Quote OSA TERTIARY for an eligible Brunei student | H123: Tertiary 50,000 | I123: contribution 380 | J123: API | K123: Not automated | L123: Not executed | M123: Not executed in this run; unit-tested in the fixed-plan engine
A124: CS-0123 | B124: TS-19 | C124: TC-064 | D124: PRD | E124: Overseas Student Assist refuses a participant who is not a Brunei citizen | F124: ag-000001 | G124: 1. Register a Malaysian passport holder 2. POST /api/v1/portal/policies/calculate OSA plan BASIC | H124: nationality MALAYSIA, registered student | I124: HTTP 422 NOT_ELIGIBLE | J124: API | K124: Executed – API run (tools/testing/api-test-run.mjs) | L124: Passed | M124: api-test-run.json EX-024: POST /api/v1/portal/policies/calculate (OSA, Malaysian participant) → 422 NOT_ELIGIBLE – The quotation does not meet the product rules [Only brunei nationals are eligible] | N124: 2 Oct 2026 22:13 UTC | O124: iorta TechNXT QA (API run)
A125: CS-0124 | B125: TS-20 | C125: TC-065 | D125: PRD | E125: FixedPlanRatingEngine: validates every catalogue product configuration | F125: Developer / CI | G125: 1. Run `npm test -w apps/api` (Vitest) 2. Locate 'FixedPlanRatingEngine validates every catalogue product configuration' in the run output | H125: Fixtures defined in modules/products/rating/fixed-plan.engine.spec.ts | I125: The test passes: FixedPlanRatingEngine validates every catalogue product configuration. | J125: Unit | K125: Automated – modules/products/rating/fixed-plan.engine.spec.ts | L125: Passed | M125: api-unit-tests.json: 'FixedPlanRatingEngine validates every catalogue product configuration' passed (2 Oct 2026 14:55 UTC); test-reruns.json: passed (2 Oct 2026 21:45 UTC) | N125: 2 Oct 2026 21:45 UTC | O125: iorta QA (Vitest)
A126: CS-0125 | B126: TS-20 | C126: TC-065 | D126: PRD | E126: Product catalogue lists the seven IIFT products with their rules | F126: ag-000001 | G126: 1. GET /api/v1/common/products 2. Check codes and the paymentBeforeIssuance / allowRenewal flags | H126: Seeded catalogue | I126: HTTP 200 with FTP-HP, FTP-NP, PFT, PHA, PRO, KHR, OSA; KHR has allowRenewal=false; PRO/KHR/OSA/PHA pay before issuance | J126: API | K126: Executed – API run (tools/testing/api-test-run.mjs) | L126: Passed | M126: api-test-run.json EX-020: GET /api/v1/common/products → FTP-HP,FTP-NP,KHR,OSA,PFT,PHA,PRO; KHR.allowRenewal=false; PRO.paymentBeforeIssuance=true | N126: 2 Oct 2026 22:13 UTC | O126: iorta TechNXT QA (API run)
A127: CS-0126 | B127: TS-20 | C127: TC-065 | D127: PRD | E127: Product configuration is maintainable without code changes | F127: manager | G127: 1. GET /api/v1/backoffice/products 2. PUT products/{KHR} with plans [] 3. PUT with the unchanged configuration | H127: Khairat product | I127: GET /backoffice/products → 7; PUT with an invalid rate table → 422 INVALID_PRODUCT_CONFIG; PUT with the unchanged configuration → 200 | J127: API | K127: Executed – API run (tools/testing/api-test-run.mjs) | L127: Passed | M127: api-test-run.json EX-117: GET /api/v1/backoffice/products; PUT products/cad06114-b5a9-48c7-ba8c-0d25df5c15a4 (plans=[]; unchanged) → 7 products | 422 INVALID_PRODUCT_CONFIG – config.plans must be a non-empty array | 200 | N127: 2 Oct 2026 22:13 UTC | O127: iorta TechNXT QA (API run)
A128: CS-0127 | B128: TS-20 | C128: TC-065 | D128: PRD | E128: Product configuration validation | F128: manager | G128: 1. Products → open a product 2. Save an invalid configuration 3. Save valid | H128: Khairat | I128: Validation error and server error shown without stack trace; valid save confirmed | J128: UI | K128: Manual (exploratory) | L128: Passed | M128: Screens: b-flow-product-invalid.png, b-flow-product-server-error.png, b-bo-products.png (evidence/ui-screens) | N128: 2 Oct 2026 | O128: iorta QA (manual, exploratory)
A129: CS-0128 | B129: TS-20 | C129: TC-066 | D129: PRD | E129: FixedPlanRatingEngine: drops risk details that the product does not define | F129: Developer / CI | G129: 1. Run `npm test -w apps/api` (Vitest) 2. Locate 'FixedPlanRatingEngine drops risk details that the product does not define' in the run output | H129: Fixtures defined in modules/products/rating/fixed-plan.engine.spec.ts | I129: The test passes: FixedPlanRatingEngine drops risk details that the product does not define. | J129: Unit | K129: Automated – modules/products/rating/fixed-plan.engine.spec.ts | L129: Passed | M129: api-unit-tests.json: 'FixedPlanRatingEngine drops risk details that the product does not define' passed (2 Oct 2026 14:55 UTC); test-reruns.json: passed (2 Oct 2026 21:45 UTC) | N129: 2 Oct 2026 21:45 UTC | O129: iorta QA (Vitest)
A130: CS-0129 | B130: TS-20 | C130: TC-066 | D130: PRD | E130: describePlan: falls back to the code for a retired plan | F130: Developer / CI | G130: 1. Run `npm test -w apps/api` (Vitest) 2. Locate 'describePlan falls back to the code for a retired plan' in the run output | H130: Fixtures defined in modules/products/plan-label.spec.ts | I130: The test passes: describePlan falls back to the code for a retired plan. | J130: Unit | K130: Automated – modules/products/plan-label.spec.ts | L130: Passed | M130: api-unit-tests.json: 'describePlan falls back to the code for a retired plan' passed (2 Oct 2026 14:55 UTC); test-reruns.json: passed (2 Oct 2026 21:45 UTC) | N130: 2 Oct 2026 21:45 UTC | O130: iorta QA (Vitest)
A131: CS-0130 | B131: TS-20 | C131: TC-066 | D131: PRD | E131: describePlan: returns null when the product has no plans | F131: Developer / CI | G131: 1. Run `npm test -w apps/api` (Vitest) 2. Locate 'describePlan returns null when the product has no plans' in the run output | H131: Fixtures defined in modules/products/plan-label.spec.ts | I131: The test passes: describePlan returns null when the product has no plans. | J131: Unit | K131: Automated – modules/products/plan-label.spec.ts | L131: Passed | M131: api-unit-tests.json: 'describePlan returns null when the product has no plans' passed (2 Oct 2026 14:55 UTC); test-reruns.json: passed (2 Oct 2026 21:45 UTC) | N131: 2 Oct 2026 21:45 UTC | O131: iorta QA (Vitest)
A132: CS-0131 | B132: TS-20 | C132: TC-066 | D132: PRD | E132: describePlan: uses the configured names | F132: Developer / CI | G132: 1. Run `npm test -w apps/api` (Vitest) 2. Locate 'describePlan uses the configured names' in the run output | H132: Fixtures defined in modules/products/plan-label.spec.ts | I132: The test passes: describePlan uses the configured names. | J132: Unit | K132: Automated – modules/products/plan-label.spec.ts | L132: Passed | M132: api-unit-tests.json: 'describePlan uses the configured names' passed (2 Oct 2026 14:55 UTC); test-reruns.json: passed (2 Oct 2026 21:45 UTC) | N132: 2 Oct 2026 21:45 UTC | O132: iorta QA (Vitest)
A133: CS-0132 | B133: TS-21 | C133: TC-067 | D133: QUO | E133: Create a quotation and save it as draft | F133: ag-000001 | G133: 1. POST /api/v1/portal/policies PRO plan B additionalCover=true | H133: Participant of EX-010 | I133: HTTP 201; status DRAFT; quotationNo QT/yy/nnnnnn; contribution 255 | J133: API | K133: Executed – API run (tools/testing/api-test-run.mjs) | L133: Passed | M133: api-test-run.json EX-030: POST /api/v1/portal/policies (PRO plan B + additional cover) → 201 QT/26/000076 DRAFT contribution=255 | N133: 2 Oct 2026 22:13 UTC | O133: iorta TechNXT QA (API run)
...

Sheet Defects
A1: ID | B1: Title | C1: Severity | D1: Priority | E1: Area | F1: Description | G1: Found by | H1: Status | I1: Cases
A2: DEF-001 | B2: End-to-end claim test uses the UTC calendar day instead of the Brunei business day | C2: Low | D2: Medium | E2: Test assets (apps/api/test/operations.e2e-spec.ts) | F2: The test 'accepts claim notifications only within the period of cover' notifies a claim dated today() in UTC. Policies seeded after 16:00 UTC start on the next Brunei day, so the claim is refused with CLAIM_NOT_VALID and the test fails when the suite runs between 16:00 and 24:00 UTC. The application behaves correctly (the same case passed in the API run with the Brunei date, EX-067). The evidence run at 14:50 UTC passed; the re-run at 22:00 UTC failed. | G2: iorta QA, re-run of the end-to-end suite on 2 October 2026 | H2: Open – fix in test code (use the business-day helper); no product change | I2: CS-0214
A3: DEF-002 | B3: Administrator password reset re-activates a disabled account | C3: Medium | D3: High | E3: User administration (apps/api/src/modules/access/users.service.ts, resetPassword) | F3: Resetting the password of a user whose status is DISABLED sets the status back to ACTIVE, and the user can sign in with the temporary password (EX-134: reset 200, sign-in 200). The audit trail records USER_PASSWORD_RESET only, not a re-activation. An administrator who resets a password should not silently re-enable an account that another administrator disabled; re-activation should be an explicit, separately audited status change (BO-03, NFR-10). The unlock function behaves correctly (it refuses disabled accounts). | G3: iorta QA, API run of 2 October 2026 | H3: Open – fix proposed: keep the status on reset and audit any re-activation; to be confirmed with IIFT | I3: CS-0268

Sheet Traceability
A1: RFP ID | B1: Area | C1: Requirement | D1: Scenarios | E1: Cases | F1: Executed | G1: Passed | H1: Failed | I1: Case IDs | J1: Coverage
A2: AP-01 | B2: Authentication | C2: Secure login | D2: TS-01 | E2: 9 | F2: 8 | G2: 8 | H2: 0 | I2: CS-0001–CS-0009 | J2: Partly executed – passed
A3: AP-02 | B3: Authentication | C3: Password management | D3: TS-02 | E3: 10 | F3: 9 | G3: 9 | H3: 0 | I3: CS-0010–CS-0019 | J3: Partly executed – passed
A4: AP-03 | B4: Authentication | C4: Session management | D4: TS-03 | E4: 13 | F4: 11 | G4: 11 | H4: 0 | I4: CS-0020–CS-0032 | J4: Partly executed – passed
A5: AP-04 | B5: Authentication | C5: Account lockout | D5: TS-04 | E5: 2 | F5: 2 | G5: 2 | H5: 0 | I5: CS-0033–CS-0034 | J5: Executed – passed
A6: AP-05 | B6: Agent/Banca profile | C6: View agent/banca profile | D6: TS-09 | E6: 4 | F6: 4 | G6: 4 | H6: 0 | I6: CS-0061–CS-0064 | J6: Executed – passed
A7: AP-06 | B7: Agent/Banca profile | C7: Maintain profile (subject to approval) | D7: TS-09 | E7: 4 | F7: 4 | G7: 4 | H7: 0 | I7: CS-0061–CS-0064 | J7: Executed – passed
A8: AP-07 | B8: Agent/Banca management | C8: Agent/banca registration | D8: TS-08 | E8: 8 | F8: 8 | G8: 8 | H8: 0 | I8: CS-0053–CS-0060 | J8: Executed – passed
A9: AP-08 | B9: Agent/Banca management | C9: Agent ID generation | D9: TS-08 | E9: 8 | F9: 8 | G9: 8 | H9: 0 | I9: CS-0053–CS-0060 | J9: Executed – passed
A10: AP-09 | B10: Agent/Banca management | C10: Main/sub-agent relationships | D10: TS-07, TS-09 | E10: 10 | F10: 10 | G10: 10 | H10: 0 | I10: CS-0047–CS-0052, CS-0061–CS-0064 | J10: Executed – passed
A11: AP-10 | B11: Agent/Banca management | C11: Agency/banca information | D11: TS-09 | E11: 4 | F11: 4 | G11: 4 | H11: 0 | I11: CS-0061–CS-0064 | J11: Executed – passed
A12: AP-11 | B12: Agent/Banca management | C12: Cross-agency participant sharing | D12: TS-07, TS-12 | E12: 11 | F12: 11 | G12: 11 | H12: 0 | I12: CS-0047–CS-0052, CS-0077–CS-0081 | J12: Executed – passed
A13: AP-12 | B13: Agent/Banca management | C13: Agency-wide participant visibility | D13: TS-07, TS-12 | E13: 11 | F13: 11 | G13: 11 | H13: 0 | I13: CS-0047–CS-0052, CS-0077–CS-0081 | J13: Executed – passed
... A140: NFR-19 | B140: Disaster recovery | C140: DR testing | D140: TS-61 | E140: 2 | F140: 0 | G140: 0 | H140: 0 | I140: CS-0326–CS-0327 | J140: Cases defined, not executed
A141: NFR-20 | B141: Maintainability | C141: Modular architecture | E141: 0 | F141: 0 | G141: 0 | H141: 0 | J141: Verified by review of the Solution Architecture (modular monolith); not a test case
A142: NFR-21 | B142: Maintainability | C142: Documentation | E142: 0 | F142: 0 | G142: 0 | H142: 0 | J142: Verified by the document pack and its rebuild from source; not a test case
A143: NFR-22 | B143: Usability | C143: User interface | D143: TS-62, TS-70 | E143: 94 | F143: 92 | G143: 92 | H143: 0 | I143: CS-0328–CS-0330, CS-0348–CS-0438 | J143: Partly executed – passed
A144: NFR-23 | B144: Usability | C144: Browser compatibility | D144: TS-62 | E144: 3 | F144: 1 | G144: 1 | H144: 0 | I144: CS-0328–CS-0330 | J144: Partly executed – passed
A145: NFR-24 | B145: Accessibility | C145: Accessibility | D145: TS-62 | E145: 3 | F145: 1 | G145: 1 | H145: 0 | I145: CS-0328–CS-0330 | J145: Partly executed – passed
A146: NFR-25 | B146: Compatibility | C146: API standards | D146: TS-64 | E146: 1 | F146: 0 | G146: 0 | H146: 0 | I146: CS-0333 | J146: Cases defined, not executed
A147: NFR-26 | B147: Monitoring | C147: System monitoring | D147: TS-60 | E147: 2 | F147: 0 | G147: 0 | H147: 0 | I147: CS-0324–CS-0325 | J147: Cases defined, not executed
A148: NFR-27 | B148: Monitoring | C148: Alerting | D148: TS-53, TS-60 | E148: 5 | F148: 2 | G148: 2 | H148: 0 | I148: CS-0290–CS-0292, CS-0324–CS-0325 | J148: Partly executed – passed
A149: NFR-28 | B149: Logging | C149: Centralised logs | D149: TS-60 | E149: 2 | F149: 0 | G149: 0 | H149: 0 | I149: CS-0324–CS-0325 | J149: Cases defined, not executed
A150: NFR-29 | B150: Data | C150: Data retention | D150: TS-65 | E150: 1 | F150: 0 | G150: 0 | H150: 0 | I150: CS-0334 | J150: Cases defined, not executed
A151: NFR-30 | B151: Data | C151: Data quality | D151: TS-11, TS-38, TS-56 | E151: 31 | F151: 29 | G151: 29 | H151: 0 | I151: CS-0071–CS-0076, CS-0217–CS-0228, CS-0304–CS-0316 | J151: Partly executed – passed
A152: DEL-09 | B152: Integration | C152: Interface specification | D152: TS-64 | E152: 1 | F152: 0 | G152: 0 | H152: 0 | I152: CS-0333 | J152: Cases defined, not executed
A153: DEL-12 | B153: Testing | C153: Test strategy | E153: 0 | F153: 0 | G153: 0 | H153: 0 | J153: This Test Strategy
A154: DEL-13 | B154: Testing | C154: SIT test cases | E154: 0 | F154: 0 | G154: 0 | H154: 0 | J154: This workbook (Scenarios, Conditions, Cases)
A155: DEL-14 | B155: Testing | C155: SIT results | E155: 0 | F155: 0 | G155: 0 | H155: 0 | J155: Execution log and evidence files of this workbook; the SIT results report follows SIT
A156: DEL-15 | B156: Testing | C156: UAT test cases | D156: TS-67 | E156: 1 | F156: 0 | G156: 0 | H156: 0 | I156: CS-0336 | J156: Cases defined, not executed
A157: DEL-16 | B157: Testing | C157: UAT results | D157: TS-67 | E157: 1 | F157: 0 | G157: 0 | H157: 0 | I157: CS-0336 | J157: Cases defined, not executed
A158: DEL-17 | B158: Security | C158: Security assessment (VAPT) | D158: TS-57 | E158: 3 | F158: 0 | G158: 0 | H158: 0 | I158: CS-0317–CS-0319 | J158: Cases defined, not executed
A159: DEL-18 | B159: Performance | C159: Performance test report | D159: TS-59 | E159: 3 | F159: 0 | G159: 0 | H159: 0 | I159: CS-0321–CS-0323 | J159: Cases defined, not executed
A160: DEL-19 | B160: Migration | C160: Data migration plan | D160: TS-66 | E160: 1 | F160: 0 | G160: 0 | H160: 0 | I160: CS-0335 | J160: Cases defined, not executed
A161: DEL-20 | B161: Deployment | C161: Deployment plan | D161: TS-68 | E161: 1 | F161: 0 | G161: 0 | H161: 0 | I161: CS-0337 | J161: Cases defined, not executed
A162: DEL-21 | B162: Deployment | C162: Go-live checklist | D162: TS-68 | E162: 1 | F162: 0 | G162: 0 | H162: 0 | I162: CS-0337 | J162: Cases defined, not executed
A163: MNT-15 | B163: Technology | C163: Browser compatibility | D163: TS-62 | E163: 3 | F163: 1 | G163: 1 | H163: 0 | I163: CS-0328–CS-0330 | J163: Partly executed – passed
A164: MNT-19 | B164: Backup | C164: Backup verification | D164: TS-61 | E164: 2 | F164: 0 | G164: 0 | H164: 0 | I164: CS-0326–CS-0327 | J164: Cases defined, not executed
A165: MNT-20 | B165: Disaster recovery | C165: DR planning and testing | D165: TS-61 | E165: 2 | F165: 0 | G165: 0 | H165: 0 | I165: CS-0326–CS-0327 | J165: Cases defined, not executed
A166: FFR01 | B166: Appendix 3 | C166: FTPHP – Financing Takaful Products (Hire Purchase) | D166: TS-15, TS-24, TS-32, TS-52 | E166: 30 | F166: 25 | G166: 25 | H166: 0 | I166: CS-0096–CS-0106, CS-0157–CS-0162, CS-0196–CS-0200, CS-0282–CS-0289 | J166: Partly executed – passed
A167: FFR02 | B167: Appendix 3 | C167: APHA – Personal Home Assistant Takaful Plan | D167: TS-18, TS-52 | E167: 10 | F167: 9 | G167: 9 | H167: 0 | I167: CS-0120–CS-0121, CS-0282–CS-0289 | J167: Partly executed – passed
... A170: FFR05 | B170: Appendix 3 | C170: APAOS – Overseas Student Takaful Plan | D170: TS-19, TS-52 | E170: 10 | F170: 8 | G170: 8 | H170: 0 | I170: CS-0122–CS-0123, CS-0282–CS-0289 | J170: Partly executed – passed

Sheet Execution log
A1: Run | B1: When | C1: Executed by | D1: Case / test | E1: Actor | F1: Request / command | G1: Expected | H1: Response / outcome | I1: Result
A2: API run RIR5X2 | B2: 2026-10-02 22:12:47 UTC | C2: iorta TechNXT QA (API run) | D2: EX-001 – Wrong password and unknown user get the same generic 401 | E2: anonymous | F2: POST /api/v1/auth/login (unknown user; finance with wrong password) | G2: HTTP 401 INVALID_CREDENTIALS for both; identical message | H2: 401 INVALID_CREDENTIALS – Invalid username or password | 401 INVALID_CREDENTIALS – Invalid username or password | I2: Passed
A3: API run RIR5X2 | B3: 2026-10-02 22:12:47 UTC | C3: iorta TechNXT QA (API run) | D3: EX-002 – Successful sign-in issues a HttpOnly SameSite=Strict cookie and a CSRF token | E3: ag-000001 | F3: POST /api/v1/auth/login | G3: HTTP 200; Set-Cookie has HttpOnly and SameSite=Strict; csrfToken present; no password hash in body | H3: 200; Set-Cookie flags: Path=/, HttpOnly, SameSite=Strict; csrfToken present | I3: Passed
A4: API run RIR5X2 | B4: 2026-10-02 22:12:47 UTC | C4: iorta TechNXT QA (API run) | D4: EX-003 – State-changing request without the CSRF token is refused | E4: ag-000001 | F4: POST /api/v1/common/notifications/read-all (no token; forged token; session token) | G4: HTTP 403 CSRF_TOKEN_INVALID without token and with a forged token; 204 with the session token | H4: 403 CSRF_TOKEN_INVALID – Security token missing or invalid. Refresh the page. | 403 CSRF_TOKEN_INVALID – Security token missing or invalid. Refresh the page. | 204 | I4: Passed
A5: API run RIR5X2 | B5: 2026-10-02 22:12:47 UTC | C5: iorta TechNXT QA (API run) | D5: EX-004 – Portal user cannot call back-office routes and vice versa | E5: ag-000001, finance | F5: GET /api/v1/backoffice/agents as agent; GET /api/v1/portal/policies as finance | G5: HTTP 403 WRONG_AUDIENCE in both directions | H5: 403 WRONG_AUDIENCE – This function is not available to your account type | 403 WRONG_AUDIENCE – This function is not available to your account type | I5: Passed
A6: API run RIR5X2 | B6: 2026-10-02 22:12:47 UTC | C6: iorta TechNXT QA (API run) | D6: EX-005 – Permission guard inside the back-office | E6: ops.maker | F6: GET /api/v1/backoffice/users | G6: HTTP 403 FORBIDDEN on user administration for the operations officer | H6: 403 FORBIDDEN – You do not have permission to perform this action | I6: Passed
A7: API run RIR5X2 | B7: 2026-10-02 22:12:47 UTC | C7: iorta TechNXT QA (API run) | D7: EX-006 – Password policy is enforced on change-password | E7: ag-000002 | F7: POST /api/v1/auth/change-password (weak new password; wrong current password) | G7: HTTP 422 PASSWORD_POLICY for a weak password; 422 CURRENT_PASSWORD_INCORRECT when the current password is wrong; the demo password is unchanged | H7: 422 PASSWORD_POLICY – Password does not meet the password policy [At least 12 characters; An upper-case letter; A symbol] | 422 CURRENT_PASSWORD_INCORRECT – Current password is incorrect | session still valid: 200 | I7: Passed
A8: API run RIR5X2 | B8: 2026-10-02 22:12:47 UTC | C8: iorta TechNXT QA (API run) | D8: EX-007 – Logout ends the session server-side | E8: ag-000003 | F8: GET /api/v1/auth/me; POST /api/v1/auth/logout; GET /api/v1/auth/me | G8: GET /auth/me 200 before logout, 401 NOT_AUTHENTICATED after | H8: 200 | 204 | 401 NOT_AUTHENTICATED – Please sign in | I8: Passed
A9: API run RIR5X2 | B9: 2026-10-02 22:12:48 UTC | C9: iorta TechNXT QA (API run) | D9: EX-008 – Signing in again ends the earlier session (single active session) | E9: ag-000003 | F9: Two sign-ins as ag-000003, then GET /api/v1/auth/me with the first cookie | G9: The first session receives 401 NOT_AUTHENTICATED after the second sign-in | H9: 401 NOT_AUTHENTICATED – Please sign in | I9: Passed
A10: API run RIR5X2 | B10: 2026-10-02 22:13:48 UTC | C10: iorta TechNXT QA (API run) | D10: EX-009 – Sub-agents see their own business; the principal sees the whole agency | E10: ag-000001, ag-000002 | F10: GET /api/v1/portal/policies as ag-000002 and as ag-000001 | G10: ag-000002 lists only policies with agent AG-000002; ag-000001 lists more policies, including those of AG-000002 | H10: sub-agent total=13 onlyOwn=true | principal total=46 includesSubAgent=true | I10: Passed
A11: API run RIR5X2 | B11: 2026-10-02 22:13:48 UTC | C11: iorta TechNXT QA (API run) | D11: EX-010 – Register an individual participant | E11: ag-000001 | F11: POST /api/v1/portal/participants (NRIC, class 1 professional) | G11: HTTP 201; participantNo PT/yy/nnnnnn; amlStatus CLEAR; IC returned masked only | H11: 201 PT/26/000076 aml=CLEAR id=*****8603 | I11: Passed
A12: API run RIR5X2 | B12: 2026-10-02 22:13:48 UTC | C12: iorta TechNXT QA (API run) | D12: EX-011 – Duplicate participant (same IC) is refused with the existing record | E12: ag-000001 | F12: POST /api/v1/portal/participants (same IC) | G12: HTTP 422 DUPLICATE_PARTICIPANT naming the existing participant number | H12: 422 DUPLICATE_PARTICIPANT – This participant is already registered as PT/26/000076 [6558a123-ebc2-4cd2-878e-79354f702c6b] | I12: Passed
... A327: Environment note | B327: 2026-10-02 21:44–21:49 UTC | C327: iorta QA | D327: First API run | E327: shared demo accounts | F327: Other engineers signed in to the same demonstration accounts from the UI during the run | G327: – | H327: Single-active-session ended 25 cases' sessions; the script now signs in again and the run was repeated (final run recorded above) | I327: Not executed
